{
  "id": "19db7ac26308178f",
  "name": "Ivan Jorge",
  "slug": "ivan-jorge",
  "last_fight_date": "2015-07-18",
  "active_current_mode": false,
  "divisions": [
    "lw",
    "ww"
  ],
  "division_names": {
    "lw": "Lightweight",
    "ww": "Welterweight"
  },
  "rank_history": {
    "p4p": [
      {
        "date": "2013-09-01",
        "rank": 243,
        "elo": 1012.71
      },
      {
        "date": "2013-10-01",
        "rank": 244,
        "elo": 1012.71
      },
      {
        "date": "2013-11-01",
        "rank": 249,
        "elo": 1012.71
      },
      {
        "date": "2013-12-01",
        "rank": 253,
        "elo": 1012.71
      },
      {
        "date": "2014-01-01",
        "rank": 260,
        "elo": 1012.71
      },
      {
        "date": "2014-02-01",
        "rank": 392,
        "elo": 988.75
      },
      {
        "date": "2014-03-01",
        "rank": 398,
        "elo": 988.75
      },
      {
        "date": "2014-04-01",
        "rank": 402,
        "elo": 988.75
      },
      {
        "date": "2014-05-01",
        "rank": 404,
        "elo": 988.75
      },
      {
        "date": "2014-06-01",
        "rank": 412,
        "elo": 988.75
      },
      {
        "date": "2014-07-01",
        "rank": 420,
        "elo": 988.75
      },
      {
        "date": "2014-08-01",
        "rank": 431,
        "elo": 988.75
      },
      {
        "date": "2014-09-01",
        "rank": 434,
        "elo": 988.75
      },
      {
        "date": "2014-10-01",
        "rank": 436,
        "elo": 988.75
      },
      {
        "date": "2014-11-01",
        "rank": 450,
        "elo": 988.75
      },
      {
        "date": "2014-12-01",
        "rank": 465,
        "elo": 988.75
      },
      {
        "date": "2015-01-01",
        "rank": 467,
        "elo": 988.75
      },
      {
        "date": "2015-02-01",
        "rank": 351,
        "elo": 1003.83
      },
      {
        "date": "2015-03-01",
        "rank": 350,
        "elo": 1003.83
      },
      {
        "date": "2015-04-01",
        "rank": 351,
        "elo": 1003.83
      },
      {
        "date": "2015-05-01",
        "rank": 351,
        "elo": 1003.83
      },
      {
        "date": "2015-06-01",
        "rank": 350,
        "elo": 1003.83
      },
      {
        "date": "2015-07-01",
        "rank": 692,
        "elo": 973.82
      },
      {
        "date": "2015-08-01",
        "rank": 701,
        "elo": 973.82
      },
      {
        "date": "2015-09-01",
        "rank": 701,
        "elo": 973.82
      },
      {
        "date": "2015-10-01",
        "rank": 696,
        "elo": 973.82
      },
      {
        "date": "2015-11-01",
        "rank": 698,
        "elo": 973.82
      },
      {
        "date": "2015-12-01",
        "rank": 705,
        "elo": 973.82
      },
      {
        "date": "2016-01-01",
        "rank": 703,
        "elo": 973.82
      },
      {
        "date": "2016-02-01",
        "rank": 704,
        "elo": 973.82
      },
      {
        "date": "2016-03-01",
        "rank": 702,
        "elo": 973.82
      },
      {
        "date": "2016-04-01",
        "rank": 703,
        "elo": 973.82
      },
      {
        "date": "2016-05-01",
        "rank": 706,
        "elo": 973.82
      },
      {
        "date": "2016-06-01",
        "rank": 703,
        "elo": 973.82
      },
      {
        "date": "2016-07-01",
        "rank": 705,
        "elo": 973.82
      },
      {
        "date": "2016-08-01",
        "rank": 710,
        "elo": 973.82
      },
      {
        "date": "2016-09-01",
        "rank": 709,
        "elo": 973.82
      },
      {
        "date": "2016-10-01",
        "rank": 712,
        "elo": 973.82
      },
      {
        "date": "2016-11-01",
        "rank": 720,
        "elo": 973.82
      },
      {
        "date": "2016-12-01",
        "rank": 720,
        "elo": 973.82
      },
      {
        "date": "2017-01-01",
        "rank": 724,
        "elo": 973.82
      },
      {
        "date": "2017-02-01",
        "rank": 724,
        "elo": 973.82
      },
      {
        "date": "2017-03-01",
        "rank": 730,
        "elo": 973.82
      },
      {
        "date": "2017-04-01",
        "rank": 722,
        "elo": 973.82
      },
      {
        "date": "2017-05-01",
        "rank": 724,
        "elo": 973.82
      },
      {
        "date": "2017-06-01",
        "rank": 730,
        "elo": 973.82
      },
      {
        "date": "2017-07-01",
        "rank": 736,
        "elo": 973.82
      },
      {
        "date": "2017-08-01",
        "rank": 735,
        "elo": 973.82
      },
      {
        "date": "2017-09-01",
        "rank": 739,
        "elo": 973.82
      },
      {
        "date": "2017-10-01",
        "rank": 742,
        "elo": 973.82
      },
      {
        "date": "2017-11-01",
        "rank": 749,
        "elo": 973.82
      },
      {
        "date": "2017-12-01",
        "rank": 756,
        "elo": 973.82
      },
      {
        "date": "2018-01-01",
        "rank": 754,
        "elo": 973.82
      },
      {
        "date": "2018-02-01",
        "rank": 757,
        "elo": 973.82
      },
      {
        "date": "2018-03-01",
        "rank": 760,
        "elo": 973.82
      },
      {
        "date": "2018-04-01",
        "rank": 759,
        "elo": 973.82
      },
      {
        "date": "2018-05-01",
        "rank": 756,
        "elo": 973.82
      },
      {
        "date": "2018-06-01",
        "rank": 758,
        "elo": 973.82
      },
      {
        "date": "2018-07-01",
        "rank": 770,
        "elo": 973.82
      },
      {
        "date": "2018-08-01",
        "rank": 774,
        "elo": 973.82
      },
      {
        "date": "2018-09-01",
        "rank": 781,
        "elo": 973.82
      },
      {
        "date": "2018-10-01",
        "rank": 778,
        "elo": 973.82
      },
      {
        "date": "2018-11-01",
        "rank": 789,
        "elo": 973.82
      },
      {
        "date": "2018-12-01",
        "rank": 789,
        "elo": 973.82
      },
      {
        "date": "2019-01-01",
        "rank": 793,
        "elo": 973.82
      },
      {
        "date": "2019-02-01",
        "rank": 806,
        "elo": 973.82
      },
      {
        "date": "2019-03-01",
        "rank": 814,
        "elo": 973.82
      },
      {
        "date": "2019-04-01",
        "rank": 819,
        "elo": 973.82
      },
      {
        "date": "2019-05-01",
        "rank": 824,
        "elo": 973.82
      },
      {
        "date": "2019-06-01",
        "rank": 827,
        "elo": 973.82
      },
      {
        "date": "2019-07-01",
        "rank": 823,
        "elo": 973.82
      },
      {
        "date": "2019-08-01",
        "rank": 829,
        "elo": 973.82
      },
      {
        "date": "2019-09-01",
        "rank": 835,
        "elo": 973.82
      },
      {
        "date": "2019-10-01",
        "rank": 846,
        "elo": 973.82
      },
      {
        "date": "2019-11-01",
        "rank": 848,
        "elo": 973.82
      },
      {
        "date": "2019-12-01",
        "rank": 848,
        "elo": 973.82
      },
      {
        "date": "2020-01-01",
        "rank": 848,
        "elo": 973.82
      },
      {
        "date": "2020-02-01",
        "rank": 848,
        "elo": 973.82
      },
      {
        "date": "2020-03-01",
        "rank": 848,
        "elo": 973.82
      },
      {
        "date": "2020-04-01",
        "rank": 848,
        "elo": 973.82
      },
      {
        "date": "2020-05-01",
        "rank": 852,
        "elo": 973.82
      },
      {
        "date": "2020-06-01",
        "rank": 861,
        "elo": 973.82
      },
      {
        "date": "2020-07-01",
        "rank": 873,
        "elo": 973.82
      },
      {
        "date": "2020-08-01",
        "rank": 889,
        "elo": 973.82
      },
      {
        "date": "2020-09-01",
        "rank": 894,
        "elo": 973.82
      },
      {
        "date": "2020-10-01",
        "rank": 907,
        "elo": 973.82
      },
      {
        "date": "2020-11-01",
        "rank": 915,
        "elo": 973.82
      },
      {
        "date": "2020-12-01",
        "rank": 914,
        "elo": 973.82
      },
      {
        "date": "2021-01-01",
        "rank": 919,
        "elo": 973.82
      },
      {
        "date": "2021-02-01",
        "rank": 919,
        "elo": 973.82
      },
      {
        "date": "2021-03-01",
        "rank": 922,
        "elo": 973.82
      },
      {
        "date": "2021-04-01",
        "rank": 925,
        "elo": 973.82
      },
      {
        "date": "2021-05-01",
        "rank": 926,
        "elo": 973.82
      },
      {
        "date": "2021-06-01",
        "rank": 921,
        "elo": 973.82
      },
      {
        "date": "2021-07-01",
        "rank": 917,
        "elo": 973.82
      },
      {
        "date": "2021-08-01",
        "rank": 923,
        "elo": 973.82
      },
      {
        "date": "2021-09-01",
        "rank": 923,
        "elo": 973.82
      },
      {
        "date": "2021-10-01",
        "rank": 923,
        "elo": 973.82
      },
      {
        "date": "2021-11-01",
        "rank": 927,
        "elo": 973.82
      },
      {
        "date": "2021-12-01",
        "rank": 924,
        "elo": 973.82
      },
      {
        "date": "2022-01-01",
        "rank": 929,
        "elo": 973.82
      },
      {
        "date": "2022-02-01",
        "rank": 937,
        "elo": 973.82
      },
      {
        "date": "2022-03-01",
        "rank": 934,
        "elo": 973.82
      },
      {
        "date": "2022-04-01",
        "rank": 944,
        "elo": 973.82
      },
      {
        "date": "2022-05-01",
        "rank": 944,
        "elo": 973.82
      },
      {
        "date": "2022-06-01",
        "rank": 943,
        "elo": 973.82
      },
      {
        "date": "2022-07-01",
        "rank": 937,
        "elo": 973.82
      },
      {
        "date": "2022-08-01",
        "rank": 942,
        "elo": 973.82
      },
      {
        "date": "2022-09-01",
        "rank": 957,
        "elo": 973.82
      },
      {
        "date": "2022-10-01",
        "rank": 951,
        "elo": 973.82
      },
      {
        "date": "2022-11-01",
        "rank": 948,
        "elo": 973.82
      },
      {
        "date": "2022-12-01",
        "rank": 947,
        "elo": 973.82
      },
      {
        "date": "2023-01-01",
        "rank": 955,
        "elo": 973.82
      },
      {
        "date": "2023-02-01",
        "rank": 972,
        "elo": 973.82
      },
      {
        "date": "2023-03-01",
        "rank": 980,
        "elo": 973.82
      },
      {
        "date": "2023-04-01",
        "rank": 981,
        "elo": 973.82
      },
      {
        "date": "2023-05-01",
        "rank": 981,
        "elo": 973.82
      },
      {
        "date": "2023-06-01",
        "rank": 978,
        "elo": 973.82
      },
      {
        "date": "2023-07-01",
        "rank": 979,
        "elo": 973.82
      },
      {
        "date": "2023-08-01",
        "rank": 980,
        "elo": 973.82
      },
      {
        "date": "2023-09-01",
        "rank": 992,
        "elo": 973.82
      },
      {
        "date": "2023-10-01",
        "rank": 988,
        "elo": 973.82
      },
      {
        "date": "2023-11-01",
        "rank": 990,
        "elo": 973.82
      },
      {
        "date": "2023-12-01",
        "rank": 991,
        "elo": 973.82
      },
      {
        "date": "2024-01-01",
        "rank": 995,
        "elo": 973.82
      },
      {
        "date": "2024-02-01",
        "rank": 997,
        "elo": 973.82
      },
      {
        "date": "2024-03-01",
        "rank": 1004,
        "elo": 973.82
      },
      {
        "date": "2024-04-01",
        "rank": 1004,
        "elo": 973.82
      },
      {
        "date": "2024-05-01",
        "rank": 1002,
        "elo": 973.82
      },
      {
        "date": "2024-06-01",
        "rank": 1005,
        "elo": 973.82
      },
      {
        "date": "2024-07-01",
        "rank": 1005,
        "elo": 973.82
      },
      {
        "date": "2024-08-01",
        "rank": 1012,
        "elo": 973.82
      },
      {
        "date": "2024-09-01",
        "rank": 1009,
        "elo": 973.82
      },
      {
        "date": "2024-10-01",
        "rank": 1010,
        "elo": 973.82
      },
      {
        "date": "2024-11-01",
        "rank": 1019,
        "elo": 973.82
      },
      {
        "date": "2024-12-01",
        "rank": 1018,
        "elo": 973.82
      },
      {
        "date": "2025-01-01",
        "rank": 1023,
        "elo": 973.82
      },
      {
        "date": "2025-02-01",
        "rank": 1031,
        "elo": 973.82
      },
      {
        "date": "2025-03-01",
        "rank": 1035,
        "elo": 973.82
      },
      {
        "date": "2025-04-01",
        "rank": 1030,
        "elo": 973.82
      },
      {
        "date": "2025-05-01",
        "rank": 1031,
        "elo": 973.82
      },
      {
        "date": "2025-06-01",
        "rank": 1033,
        "elo": 973.82
      },
      {
        "date": "2025-07-01",
        "rank": 1029,
        "elo": 973.82
      },
      {
        "date": "2025-08-01",
        "rank": 1031,
        "elo": 973.82
      },
      {
        "date": "2025-09-01",
        "rank": 1040,
        "elo": 973.82
      },
      {
        "date": "2025-10-01",
        "rank": 1043,
        "elo": 973.82
      },
      {
        "date": "2025-11-01",
        "rank": 1049,
        "elo": 973.82
      },
      {
        "date": "2025-12-01",
        "rank": 1055,
        "elo": 973.82
      },
      {
        "date": "2026-01-01",
        "rank": 1062,
        "elo": 973.82
      },
      {
        "date": "2026-02-01",
        "rank": 1061,
        "elo": 973.82
      },
      {
        "date": "2026-03-01",
        "rank": 1067,
        "elo": 973.82
      },
      {
        "date": "2026-04-01",
        "rank": 1070,
        "elo": 973.82
      },
      {
        "date": "2026-05-01",
        "rank": 1068,
        "elo": 973.82
      },
      {
        "date": "2026-06-01",
        "rank": 1066,
        "elo": 973.82
      }
    ],
    "lw": [
      {
        "date": "2014-02-01",
        "rank": 129,
        "elo": 976.0
      },
      {
        "date": "2014-03-01",
        "rank": 139,
        "elo": 976.0
      },
      {
        "date": "2014-04-01",
        "rank": 140,
        "elo": 976.0
      },
      {
        "date": "2014-05-01",
        "rank": 143,
        "elo": 976.0
      },
      {
        "date": "2014-06-01",
        "rank": 148,
        "elo": 976.0
      },
      {
        "date": "2014-07-01",
        "rank": 148,
        "elo": 976.0
      },
      {
        "date": "2014-08-01",
        "rank": 144,
        "elo": 976.0
      },
      {
        "date": "2014-09-01",
        "rank": 145,
        "elo": 976.0
      },
      {
        "date": "2014-10-01",
        "rank": 150,
        "elo": 976.0
      },
      {
        "date": "2014-11-01",
        "rank": 157,
        "elo": 976.0
      },
      {
        "date": "2014-12-01",
        "rank": 159,
        "elo": 976.0
      },
      {
        "date": "2015-01-01",
        "rank": 159,
        "elo": 976.0
      },
      {
        "date": "2015-02-01",
        "rank": 115,
        "elo": 991.67
      },
      {
        "date": "2015-03-01",
        "rank": 115,
        "elo": 991.67
      },
      {
        "date": "2015-04-01",
        "rank": 114,
        "elo": 991.67
      },
      {
        "date": "2015-05-01",
        "rank": 113,
        "elo": 991.67
      },
      {
        "date": "2015-06-01",
        "rank": 111,
        "elo": 991.67
      },
      {
        "date": "2015-07-01",
        "rank": 248,
        "elo": 962.76
      },
      {
        "date": "2015-08-01",
        "rank": 252,
        "elo": 962.76
      },
      {
        "date": "2015-09-01",
        "rank": 255,
        "elo": 962.76
      },
      {
        "date": "2015-10-01",
        "rank": 255,
        "elo": 962.76
      },
      {
        "date": "2015-11-01",
        "rank": 255,
        "elo": 962.76
      },
      {
        "date": "2015-12-01",
        "rank": 259,
        "elo": 962.76
      },
      {
        "date": "2016-01-01",
        "rank": 262,
        "elo": 962.76
      },
      {
        "date": "2016-02-01",
        "rank": 266,
        "elo": 962.76
      },
      {
        "date": "2016-03-01",
        "rank": 267,
        "elo": 962.76
      },
      {
        "date": "2016-04-01",
        "rank": 268,
        "elo": 962.76
      },
      {
        "date": "2016-05-01",
        "rank": 269,
        "elo": 962.76
      },
      {
        "date": "2016-06-01",
        "rank": 269,
        "elo": 962.76
      },
      {
        "date": "2016-07-01",
        "rank": 269,
        "elo": 962.76
      },
      {
        "date": "2016-08-01",
        "rank": 273,
        "elo": 962.76
      },
      {
        "date": "2016-09-01",
        "rank": 276,
        "elo": 962.76
      },
      {
        "date": "2016-10-01",
        "rank": 277,
        "elo": 962.76
      },
      {
        "date": "2016-11-01",
        "rank": 280,
        "elo": 962.76
      },
      {
        "date": "2016-12-01",
        "rank": 278,
        "elo": 962.76
      },
      {
        "date": "2017-01-01",
        "rank": 279,
        "elo": 962.76
      },
      {
        "date": "2017-02-01",
        "rank": 278,
        "elo": 962.76
      },
      {
        "date": "2017-03-01",
        "rank": 278,
        "elo": 962.76
      },
      {
        "date": "2017-04-01",
        "rank": 277,
        "elo": 962.76
      },
      {
        "date": "2017-05-01",
        "rank": 277,
        "elo": 962.76
      },
      {
        "date": "2017-06-01",
        "rank": 277,
        "elo": 962.76
      },
      {
        "date": "2017-07-01",
        "rank": 278,
        "elo": 962.76
      },
      {
        "date": "2017-08-01",
        "rank": 279,
        "elo": 962.76
      },
      {
        "date": "2017-09-01",
        "rank": 278,
        "elo": 962.76
      },
      {
        "date": "2017-10-01",
        "rank": 281,
        "elo": 962.76
      },
      {
        "date": "2017-11-01",
        "rank": 282,
        "elo": 962.76
      },
      {
        "date": "2017-12-01",
        "rank": 284,
        "elo": 962.76
      },
      {
        "date": "2018-01-01",
        "rank": 284,
        "elo": 962.76
      },
      {
        "date": "2018-02-01",
        "rank": 285,
        "elo": 962.76
      },
      {
        "date": "2018-03-01",
        "rank": 286,
        "elo": 962.76
      },
      {
        "date": "2018-04-01",
        "rank": 285,
        "elo": 962.76
      },
      {
        "date": "2018-05-01",
        "rank": 284,
        "elo": 962.76
      },
      {
        "date": "2018-06-01",
        "rank": 283,
        "elo": 962.76
      },
      {
        "date": "2018-07-01",
        "rank": 288,
        "elo": 962.76
      },
      {
        "date": "2018-08-01",
        "rank": 288,
        "elo": 962.76
      },
      {
        "date": "2018-09-01",
        "rank": 287,
        "elo": 962.76
      },
      {
        "date": "2018-10-01",
        "rank": 289,
        "elo": 962.76
      },
      {
        "date": "2018-11-01",
        "rank": 291,
        "elo": 962.76
      },
      {
        "date": "2018-12-01",
        "rank": 291,
        "elo": 962.76
      },
      {
        "date": "2019-01-01",
        "rank": 290,
        "elo": 962.76
      },
      {
        "date": "2019-02-01",
        "rank": 295,
        "elo": 962.76
      },
      {
        "date": "2019-03-01",
        "rank": 294,
        "elo": 962.76
      },
      {
        "date": "2019-04-01",
        "rank": 301,
        "elo": 962.76
      },
      {
        "date": "2019-05-01",
        "rank": 304,
        "elo": 962.76
      },
      {
        "date": "2019-06-01",
        "rank": 306,
        "elo": 962.76
      },
      {
        "date": "2019-07-01",
        "rank": 306,
        "elo": 962.76
      },
      {
        "date": "2019-08-01",
        "rank": 306,
        "elo": 962.76
      },
      {
        "date": "2019-09-01",
        "rank": 306,
        "elo": 962.76
      },
      {
        "date": "2019-10-01",
        "rank": 307,
        "elo": 962.76
      },
      {
        "date": "2019-11-01",
        "rank": 306,
        "elo": 962.76
      },
      {
        "date": "2019-12-01",
        "rank": 307,
        "elo": 962.76
      },
      {
        "date": "2020-01-01",
        "rank": 307,
        "elo": 962.76
      },
      {
        "date": "2020-02-01",
        "rank": 307,
        "elo": 962.76
      },
      {
        "date": "2020-03-01",
        "rank": 307,
        "elo": 962.76
      },
      {
        "date": "2020-04-01",
        "rank": 307,
        "elo": 962.76
      },
      {
        "date": "2020-05-01",
        "rank": 310,
        "elo": 962.76
      },
      {
        "date": "2020-06-01",
        "rank": 314,
        "elo": 962.76
      },
      {
        "date": "2020-07-01",
        "rank": 315,
        "elo": 962.76
      },
      {
        "date": "2020-08-01",
        "rank": 316,
        "elo": 962.76
      },
      {
        "date": "2020-09-01",
        "rank": 316,
        "elo": 962.76
      },
      {
        "date": "2020-10-01",
        "rank": 317,
        "elo": 962.76
      },
      {
        "date": "2020-11-01",
        "rank": 317,
        "elo": 962.76
      },
      {
        "date": "2020-12-01",
        "rank": 317,
        "elo": 962.76
      },
      {
        "date": "2021-01-01",
        "rank": 319,
        "elo": 962.76
      },
      {
        "date": "2021-02-01",
        "rank": 319,
        "elo": 962.76
      },
      {
        "date": "2021-03-01",
        "rank": 324,
        "elo": 962.76
      },
      {
        "date": "2021-04-01",
        "rank": 325,
        "elo": 962.76
      },
      {
        "date": "2021-05-01",
        "rank": 328,
        "elo": 962.76
      },
      {
        "date": "2021-06-01",
        "rank": 328,
        "elo": 962.76
      },
      {
        "date": "2021-07-01",
        "rank": 326,
        "elo": 962.76
      },
      {
        "date": "2021-08-01",
        "rank": 326,
        "elo": 962.76
      },
      {
        "date": "2021-09-01",
        "rank": 327,
        "elo": 962.76
      },
      {
        "date": "2021-10-01",
        "rank": 334,
        "elo": 962.76
      },
      {
        "date": "2021-11-01",
        "rank": 335,
        "elo": 962.76
      },
      {
        "date": "2021-12-01",
        "rank": 335,
        "elo": 962.76
      },
      {
        "date": "2022-01-01",
        "rank": 338,
        "elo": 962.76
      },
      {
        "date": "2022-02-01",
        "rank": 339,
        "elo": 962.76
      },
      {
        "date": "2022-03-01",
        "rank": 339,
        "elo": 962.76
      },
      {
        "date": "2022-04-01",
        "rank": 337,
        "elo": 962.76
      },
      {
        "date": "2022-05-01",
        "rank": 336,
        "elo": 962.76
      },
      {
        "date": "2022-06-01",
        "rank": 338,
        "elo": 962.76
      },
      {
        "date": "2022-07-01",
        "rank": 336,
        "elo": 962.76
      },
      {
        "date": "2022-08-01",
        "rank": 334,
        "elo": 962.76
      },
      {
        "date": "2022-09-01",
        "rank": 338,
        "elo": 962.76
      },
      {
        "date": "2022-10-01",
        "rank": 338,
        "elo": 962.76
      },
      {
        "date": "2022-11-01",
        "rank": 337,
        "elo": 962.76
      },
      {
        "date": "2022-12-01",
        "rank": 334,
        "elo": 962.76
      },
      {
        "date": "2023-01-01",
        "rank": 338,
        "elo": 962.76
      },
      {
        "date": "2023-02-01",
        "rank": 348,
        "elo": 962.76
      },
      {
        "date": "2023-03-01",
        "rank": 353,
        "elo": 962.76
      },
      {
        "date": "2023-04-01",
        "rank": 351,
        "elo": 962.76
      },
      {
        "date": "2023-05-01",
        "rank": 350,
        "elo": 962.76
      },
      {
        "date": "2023-06-01",
        "rank": 351,
        "elo": 962.76
      },
      {
        "date": "2023-07-01",
        "rank": 351,
        "elo": 962.76
      },
      {
        "date": "2023-08-01",
        "rank": 351,
        "elo": 962.76
      },
      {
        "date": "2023-09-01",
        "rank": 353,
        "elo": 962.76
      },
      {
        "date": "2023-10-01",
        "rank": 355,
        "elo": 962.76
      },
      {
        "date": "2023-11-01",
        "rank": 357,
        "elo": 962.76
      },
      {
        "date": "2023-12-01",
        "rank": 356,
        "elo": 962.76
      },
      {
        "date": "2024-01-01",
        "rank": 358,
        "elo": 962.76
      },
      {
        "date": "2024-02-01",
        "rank": 361,
        "elo": 962.76
      },
      {
        "date": "2024-03-01",
        "rank": 364,
        "elo": 962.76
      },
      {
        "date": "2024-04-01",
        "rank": 366,
        "elo": 962.76
      },
      {
        "date": "2024-05-01",
        "rank": 366,
        "elo": 962.76
      },
      {
        "date": "2024-06-01",
        "rank": 365,
        "elo": 962.76
      },
      {
        "date": "2024-07-01",
        "rank": 367,
        "elo": 962.76
      },
      {
        "date": "2024-08-01",
        "rank": 368,
        "elo": 962.76
      },
      {
        "date": "2024-09-01",
        "rank": 365,
        "elo": 962.76
      },
      {
        "date": "2024-10-01",
        "rank": 365,
        "elo": 962.76
      },
      {
        "date": "2024-11-01",
        "rank": 364,
        "elo": 962.76
      },
      {
        "date": "2024-12-01",
        "rank": 363,
        "elo": 962.76
      },
      {
        "date": "2025-01-01",
        "rank": 363,
        "elo": 962.76
      },
      {
        "date": "2025-02-01",
        "rank": 363,
        "elo": 962.76
      },
      {
        "date": "2025-03-01",
        "rank": 359,
        "elo": 962.76
      },
      {
        "date": "2025-04-01",
        "rank": 359,
        "elo": 962.76
      },
      {
        "date": "2025-05-01",
        "rank": 363,
        "elo": 962.76
      },
      {
        "date": "2025-06-01",
        "rank": 364,
        "elo": 962.76
      },
      {
        "date": "2025-07-01",
        "rank": 364,
        "elo": 962.76
      },
      {
        "date": "2025-08-01",
        "rank": 364,
        "elo": 962.76
      },
      {
        "date": "2025-09-01",
        "rank": 364,
        "elo": 962.76
      },
      {
        "date": "2025-10-01",
        "rank": 364,
        "elo": 962.76
      },
      {
        "date": "2025-11-01",
        "rank": 364,
        "elo": 962.76
      },
      {
        "date": "2025-12-01",
        "rank": 363,
        "elo": 962.76
      },
      {
        "date": "2026-01-01",
        "rank": 365,
        "elo": 962.76
      },
      {
        "date": "2026-02-01",
        "rank": 365,
        "elo": 962.76
      },
      {
        "date": "2026-03-01",
        "rank": 366,
        "elo": 962.76
      },
      {
        "date": "2026-04-01",
        "rank": 370,
        "elo": 962.76
      },
      {
        "date": "2026-05-01",
        "rank": 371,
        "elo": 962.76
      },
      {
        "date": "2026-06-01",
        "rank": 371,
        "elo": 962.76
      }
    ],
    "ww": [
      {
        "date": "2013-09-01",
        "rank": 56,
        "elo": 1012.76
      },
      {
        "date": "2013-10-01",
        "rank": 58,
        "elo": 1012.76
      },
      {
        "date": "2013-11-01",
        "rank": 60,
        "elo": 1012.76
      },
      {
        "date": "2013-12-01",
        "rank": 60,
        "elo": 1012.76
      },
      {
        "date": "2014-01-01",
        "rank": 63,
        "elo": 1012.76
      },
      {
        "date": "2014-02-01",
        "rank": 62,
        "elo": 1012.76
      },
      {
        "date": "2014-03-01",
        "rank": 61,
        "elo": 1012.76
      },
      {
        "date": "2014-04-01",
        "rank": 61,
        "elo": 1012.76
      },
      {
        "date": "2014-05-01",
        "rank": 60,
        "elo": 1012.76
      },
      {
        "date": "2014-06-01",
        "rank": 61,
        "elo": 1012.76
      },
      {
        "date": "2014-07-01",
        "rank": 61,
        "elo": 1012.76
      },
      {
        "date": "2014-08-01",
        "rank": 63,
        "elo": 1012.76
      },
      {
        "date": "2014-09-01",
        "rank": 61,
        "elo": 1012.76
      },
      {
        "date": "2014-10-01",
        "rank": 61,
        "elo": 1012.76
      },
      {
        "date": "2014-11-01",
        "rank": 62,
        "elo": 1012.76
      },
      {
        "date": "2014-12-01",
        "rank": 62,
        "elo": 1012.76
      },
      {
        "date": "2015-01-01",
        "rank": 63,
        "elo": 1012.76
      },
      {
        "date": "2015-02-01",
        "rank": 66,
        "elo": 1012.76
      },
      {
        "date": "2015-03-01",
        "rank": 67,
        "elo": 1012.76
      },
      {
        "date": "2015-04-01",
        "rank": 68,
        "elo": 1012.76
      },
      {
        "date": "2015-05-01",
        "rank": 71,
        "elo": 1012.76
      },
      {
        "date": "2015-06-01",
        "rank": 69,
        "elo": 1012.76
      },
      {
        "date": "2015-07-01",
        "rank": 74,
        "elo": 1012.76
      },
      {
        "date": "2015-08-01",
        "rank": 72,
        "elo": 1012.76
      },
      {
        "date": "2015-09-01",
        "rank": 71,
        "elo": 1012.76
      },
      {
        "date": "2015-10-01",
        "rank": 69,
        "elo": 1012.76
      },
      {
        "date": "2015-11-01",
        "rank": 72,
        "elo": 1012.76
      },
      {
        "date": "2015-12-01",
        "rank": 73,
        "elo": 1012.76
      },
      {
        "date": "2016-01-01",
        "rank": 73,
        "elo": 1012.76
      },
      {
        "date": "2016-02-01",
        "rank": 74,
        "elo": 1012.76
      },
      {
        "date": "2016-03-01",
        "rank": 76,
        "elo": 1012.76
      },
      {
        "date": "2016-04-01",
        "rank": 75,
        "elo": 1012.76
      },
      {
        "date": "2016-05-01",
        "rank": 75,
        "elo": 1012.76
      },
      {
        "date": "2016-06-01",
        "rank": 75,
        "elo": 1012.76
      },
      {
        "date": "2016-07-01",
        "rank": 74,
        "elo": 1012.76
      },
      {
        "date": "2016-08-01",
        "rank": 72,
        "elo": 1012.76
      },
      {
        "date": "2016-09-01",
        "rank": 73,
        "elo": 1012.76
      },
      {
        "date": "2016-10-01",
        "rank": 73,
        "elo": 1012.76
      },
      {
        "date": "2016-11-01",
        "rank": 74,
        "elo": 1012.76
      },
      {
        "date": "2016-12-01",
        "rank": 79,
        "elo": 1012.76
      },
      {
        "date": "2017-01-01",
        "rank": 80,
        "elo": 1012.76
      },
      {
        "date": "2017-02-01",
        "rank": 78,
        "elo": 1012.76
      },
      {
        "date": "2017-03-01",
        "rank": 78,
        "elo": 1012.76
      },
      {
        "date": "2017-04-01",
        "rank": 76,
        "elo": 1012.76
      },
      {
        "date": "2017-05-01",
        "rank": 74,
        "elo": 1012.76
      },
      {
        "date": "2017-06-01",
        "rank": 75,
        "elo": 1012.76
      },
      {
        "date": "2017-07-01",
        "rank": 79,
        "elo": 1012.76
      },
      {
        "date": "2017-08-01",
        "rank": 78,
        "elo": 1012.76
      },
      {
        "date": "2017-09-01",
        "rank": 77,
        "elo": 1012.76
      },
      {
        "date": "2017-10-01",
        "rank": 76,
        "elo": 1012.76
      },
      {
        "date": "2017-11-01",
        "rank": 80,
        "elo": 1012.76
      },
      {
        "date": "2017-12-01",
        "rank": 80,
        "elo": 1012.76
      },
      {
        "date": "2018-01-01",
        "rank": 80,
        "elo": 1012.76
      },
      {
        "date": "2018-02-01",
        "rank": 82,
        "elo": 1012.76
      },
      {
        "date": "2018-03-01",
        "rank": 82,
        "elo": 1012.76
      },
      {
        "date": "2018-04-01",
        "rank": 84,
        "elo": 1012.76
      },
      {
        "date": "2018-05-01",
        "rank": 84,
        "elo": 1012.76
      },
      {
        "date": "2018-06-01",
        "rank": 83,
        "elo": 1012.76
      },
      {
        "date": "2018-07-01",
        "rank": 83,
        "elo": 1012.76
      },
      {
        "date": "2018-08-01",
        "rank": 82,
        "elo": 1012.76
      },
      {
        "date": "2018-09-01",
        "rank": 82,
        "elo": 1012.76
      },
      {
        "date": "2018-10-01",
        "rank": 83,
        "elo": 1012.76
      },
      {
        "date": "2018-11-01",
        "rank": 84,
        "elo": 1012.76
      },
      {
        "date": "2018-12-01",
        "rank": 83,
        "elo": 1012.76
      },
      {
        "date": "2019-01-01",
        "rank": 82,
        "elo": 1012.76
      },
      {
        "date": "2019-02-01",
        "rank": 81,
        "elo": 1012.76
      },
      {
        "date": "2019-03-01",
        "rank": 82,
        "elo": 1012.76
      },
      {
        "date": "2019-04-01",
        "rank": 83,
        "elo": 1012.76
      },
      {
        "date": "2019-05-01",
        "rank": 85,
        "elo": 1012.76
      },
      {
        "date": "2019-06-01",
        "rank": 86,
        "elo": 1012.76
      },
      {
        "date": "2019-07-01",
        "rank": 85,
        "elo": 1012.76
      },
      {
        "date": "2019-08-01",
        "rank": 84,
        "elo": 1012.76
      },
      {
        "date": "2019-09-01",
        "rank": 83,
        "elo": 1012.76
      },
      {
        "date": "2019-10-01",
        "rank": 87,
        "elo": 1012.76
      },
      {
        "date": "2019-11-01",
        "rank": 84,
        "elo": 1012.76
      },
      {
        "date": "2019-12-01",
        "rank": 84,
        "elo": 1012.76
      },
      {
        "date": "2020-01-01",
        "rank": 84,
        "elo": 1012.76
      },
      {
        "date": "2020-02-01",
        "rank": 84,
        "elo": 1012.76
      },
      {
        "date": "2020-03-01",
        "rank": 84,
        "elo": 1012.76
      },
      {
        "date": "2020-04-01",
        "rank": 84,
        "elo": 1012.76
      },
      {
        "date": "2020-05-01",
        "rank": 84,
        "elo": 1012.76
      },
      {
        "date": "2020-06-01",
        "rank": 83,
        "elo": 1012.76
      },
      {
        "date": "2020-07-01",
        "rank": 86,
        "elo": 1012.76
      },
      {
        "date": "2020-08-01",
        "rank": 85,
        "elo": 1012.76
      },
      {
        "date": "2020-09-01",
        "rank": 84,
        "elo": 1012.76
      },
      {
        "date": "2020-10-01",
        "rank": 85,
        "elo": 1012.76
      },
      {
        "date": "2020-11-01",
        "rank": 85,
        "elo": 1012.76
      },
      {
        "date": "2020-12-01",
        "rank": 85,
        "elo": 1012.76
      },
      {
        "date": "2021-01-01",
        "rank": 85,
        "elo": 1012.76
      },
      {
        "date": "2021-02-01",
        "rank": 85,
        "elo": 1012.76
      },
      {
        "date": "2021-03-01",
        "rank": 84,
        "elo": 1012.76
      },
      {
        "date": "2021-04-01",
        "rank": 86,
        "elo": 1012.76
      },
      {
        "date": "2021-05-01",
        "rank": 87,
        "elo": 1012.76
      },
      {
        "date": "2021-06-01",
        "rank": 87,
        "elo": 1012.76
      },
      {
        "date": "2021-07-01",
        "rank": 88,
        "elo": 1012.76
      },
      {
        "date": "2021-08-01",
        "rank": 88,
        "elo": 1012.76
      },
      {
        "date": "2021-09-01",
        "rank": 88,
        "elo": 1012.76
      },
      {
        "date": "2021-10-01",
        "rank": 88,
        "elo": 1012.76
      },
      {
        "date": "2021-11-01",
        "rank": 87,
        "elo": 1012.76
      },
      {
        "date": "2021-12-01",
        "rank": 86,
        "elo": 1012.76
      },
      {
        "date": "2022-01-01",
        "rank": 88,
        "elo": 1012.76
      },
      {
        "date": "2022-02-01",
        "rank": 88,
        "elo": 1012.76
      },
      {
        "date": "2022-03-01",
        "rank": 89,
        "elo": 1012.76
      },
      {
        "date": "2022-04-01",
        "rank": 91,
        "elo": 1012.76
      },
      {
        "date": "2022-05-01",
        "rank": 92,
        "elo": 1012.76
      },
      {
        "date": "2022-06-01",
        "rank": 91,
        "elo": 1012.76
      },
      {
        "date": "2022-07-01",
        "rank": 91,
        "elo": 1012.76
      },
      {
        "date": "2022-08-01",
        "rank": 92,
        "elo": 1012.76
      },
      {
        "date": "2022-09-01",
        "rank": 91,
        "elo": 1012.76
      },
      {
        "date": "2022-10-01",
        "rank": 90,
        "elo": 1012.76
      },
      {
        "date": "2022-11-01",
        "rank": 90,
        "elo": 1012.76
      },
      {
        "date": "2022-12-01",
        "rank": 86,
        "elo": 1012.76
      },
      {
        "date": "2023-01-01",
        "rank": 87,
        "elo": 1012.76
      },
      {
        "date": "2023-02-01",
        "rank": 87,
        "elo": 1012.76
      },
      {
        "date": "2023-03-01",
        "rank": 88,
        "elo": 1012.76
      },
      {
        "date": "2023-04-01",
        "rank": 89,
        "elo": 1012.76
      },
      {
        "date": "2023-05-01",
        "rank": 91,
        "elo": 1012.76
      },
      {
        "date": "2023-06-01",
        "rank": 92,
        "elo": 1012.76
      },
      {
        "date": "2023-07-01",
        "rank": 94,
        "elo": 1012.76
      },
      {
        "date": "2023-08-01",
        "rank": 95,
        "elo": 1012.76
      },
      {
        "date": "2023-09-01",
        "rank": 97,
        "elo": 1012.76
      },
      {
        "date": "2023-10-01",
        "rank": 97,
        "elo": 1012.76
      },
      {
        "date": "2023-11-01",
        "rank": 95,
        "elo": 1012.76
      },
      {
        "date": "2023-12-01",
        "rank": 95,
        "elo": 1012.76
      },
      {
        "date": "2024-01-01",
        "rank": 96,
        "elo": 1012.76
      },
      {
        "date": "2024-02-01",
        "rank": 97,
        "elo": 1012.76
      },
      {
        "date": "2024-03-01",
        "rank": 97,
        "elo": 1012.76
      },
      {
        "date": "2024-04-01",
        "rank": 97,
        "elo": 1012.76
      },
      {
        "date": "2024-05-01",
        "rank": 97,
        "elo": 1012.76
      },
      {
        "date": "2024-06-01",
        "rank": 96,
        "elo": 1012.76
      },
      {
        "date": "2024-07-01",
        "rank": 96,
        "elo": 1012.76
      },
      {
        "date": "2024-08-01",
        "rank": 96,
        "elo": 1012.76
      },
      {
        "date": "2024-09-01",
        "rank": 95,
        "elo": 1012.76
      },
      {
        "date": "2024-10-01",
        "rank": 94,
        "elo": 1012.76
      },
      {
        "date": "2024-11-01",
        "rank": 95,
        "elo": 1012.76
      },
      {
        "date": "2024-12-01",
        "rank": 95,
        "elo": 1012.76
      },
      {
        "date": "2025-01-01",
        "rank": 96,
        "elo": 1012.76
      },
      {
        "date": "2025-02-01",
        "rank": 97,
        "elo": 1012.76
      },
      {
        "date": "2025-03-01",
        "rank": 96,
        "elo": 1012.76
      },
      {
        "date": "2025-04-01",
        "rank": 95,
        "elo": 1012.76
      },
      {
        "date": "2025-05-01",
        "rank": 93,
        "elo": 1012.76
      },
      {
        "date": "2025-06-01",
        "rank": 95,
        "elo": 1012.76
      },
      {
        "date": "2025-07-01",
        "rank": 96,
        "elo": 1012.76
      },
      {
        "date": "2025-08-01",
        "rank": 96,
        "elo": 1012.76
      },
      {
        "date": "2025-09-01",
        "rank": 96,
        "elo": 1012.76
      },
      {
        "date": "2025-10-01",
        "rank": 97,
        "elo": 1012.76
      },
      {
        "date": "2025-11-01",
        "rank": 97,
        "elo": 1012.76
      },
      {
        "date": "2025-12-01",
        "rank": 97,
        "elo": 1012.76
      },
      {
        "date": "2026-01-01",
        "rank": 97,
        "elo": 1012.76
      },
      {
        "date": "2026-02-01",
        "rank": 95,
        "elo": 1012.76
      },
      {
        "date": "2026-03-01",
        "rank": 96,
        "elo": 1012.76
      },
      {
        "date": "2026-04-01",
        "rank": 99,
        "elo": 1012.76
      },
      {
        "date": "2026-05-01",
        "rank": 99,
        "elo": 1012.76
      },
      {
        "date": "2026-06-01",
        "rank": 99,
        "elo": 1012.76
      }
    ]
  },
  "fights": [
    {
      "date": "2015-07-18",
      "weight_class": "lw",
      "weight_class_name": "Lightweight",
      "opponent_id": "654ae722109a0d31",
      "opponent_name": "Joe Duffy",
      "result": "sub",
      "outcome": "L",
      "p4p_before": 1003.83,
      "p4p_after": 973.82,
      "p4p_delta": -30.01,
      "div_before": 991.67,
      "div_after": 962.76,
      "div_delta": -28.91
    },
    {
      "date": "2015-02-22",
      "weight_class": "lw",
      "weight_class_name": "Lightweight",
      "opponent_id": "1d36f1ac66cf689d",
      "opponent_name": "Josh Shockley",
      "result": "ud",
      "outcome": "W",
      "p4p_before": 988.75,
      "p4p_after": 1003.83,
      "p4p_delta": 15.08,
      "div_before": 976.0,
      "div_after": 991.67,
      "div_delta": 15.67
    },
    {
      "date": "2014-02-15",
      "weight_class": "lw",
      "weight_class_name": "Lightweight",
      "opponent_id": "a20d7dfaba74c067",
      "opponent_name": "Rodrigo Damm",
      "result": "ud",
      "outcome": "L",
      "p4p_before": 1012.71,
      "p4p_after": 988.75,
      "p4p_delta": -23.96,
      "div_before": 1000.0,
      "div_after": 976.0,
      "div_delta": -24.0
    },
    {
      "date": "2013-09-04",
      "weight_class": "ww",
      "weight_class_name": "Welterweight",
      "opponent_id": "cd12227edd3f134b",
      "opponent_name": "Keith Wisniewski",
      "result": "ud",
      "outcome": "W",
      "p4p_before": 1000.0,
      "p4p_after": 1012.71,
      "p4p_delta": 12.71,
      "div_before": 1000.0,
      "div_after": 1012.76,
      "div_delta": 12.76
    }
  ]
}