{
  "id": "6ad8e4296f7522d9",
  "name": "Igor Severino",
  "slug": "igor-severino",
  "last_fight_date": "2024-03-23",
  "active_current_mode": false,
  "divisions": [
    "flw"
  ],
  "division_names": {
    "flw": "Flyweight"
  },
  "rank_history": {
    "p4p": [
      {
        "date": "2024-03-01",
        "rank": 950,
        "elo": 976.0
      },
      {
        "date": "2024-04-01",
        "rank": 952,
        "elo": 976.0
      },
      {
        "date": "2024-05-01",
        "rank": 951,
        "elo": 976.0
      },
      {
        "date": "2024-06-01",
        "rank": 952,
        "elo": 976.0
      },
      {
        "date": "2024-07-01",
        "rank": 954,
        "elo": 976.0
      },
      {
        "date": "2024-08-01",
        "rank": 962,
        "elo": 976.0
      },
      {
        "date": "2024-09-01",
        "rank": 959,
        "elo": 976.0
      },
      {
        "date": "2024-10-01",
        "rank": 960,
        "elo": 976.0
      },
      {
        "date": "2024-11-01",
        "rank": 966,
        "elo": 976.0
      },
      {
        "date": "2024-12-01",
        "rank": 965,
        "elo": 976.0
      },
      {
        "date": "2025-01-01",
        "rank": 968,
        "elo": 976.0
      },
      {
        "date": "2025-02-01",
        "rank": 978,
        "elo": 976.0
      },
      {
        "date": "2025-03-01",
        "rank": 982,
        "elo": 976.0
      },
      {
        "date": "2025-04-01",
        "rank": 978,
        "elo": 976.0
      },
      {
        "date": "2025-05-01",
        "rank": 978,
        "elo": 976.0
      },
      {
        "date": "2025-06-01",
        "rank": 980,
        "elo": 976.0
      },
      {
        "date": "2025-07-01",
        "rank": 973,
        "elo": 976.0
      },
      {
        "date": "2025-08-01",
        "rank": 975,
        "elo": 976.0
      },
      {
        "date": "2025-09-01",
        "rank": 987,
        "elo": 976.0
      },
      {
        "date": "2025-10-01",
        "rank": 991,
        "elo": 976.0
      },
      {
        "date": "2025-11-01",
        "rank": 995,
        "elo": 976.0
      },
      {
        "date": "2025-12-01",
        "rank": 1001,
        "elo": 976.0
      },
      {
        "date": "2026-01-01",
        "rank": 1009,
        "elo": 976.0
      },
      {
        "date": "2026-02-01",
        "rank": 1008,
        "elo": 976.0
      },
      {
        "date": "2026-03-01",
        "rank": 1012,
        "elo": 976.0
      },
      {
        "date": "2026-04-01",
        "rank": 1013,
        "elo": 976.0
      },
      {
        "date": "2026-05-01",
        "rank": 1010,
        "elo": 976.0
      },
      {
        "date": "2026-06-01",
        "rank": 1008,
        "elo": 976.0
      }
    ],
    "flw": [
      {
        "date": "2024-03-01",
        "rank": 63,
        "elo": 976.0
      },
      {
        "date": "2024-04-01",
        "rank": 65,
        "elo": 976.0
      },
      {
        "date": "2024-05-01",
        "rank": 63,
        "elo": 976.0
      },
      {
        "date": "2024-06-01",
        "rank": 65,
        "elo": 976.0
      },
      {
        "date": "2024-07-01",
        "rank": 63,
        "elo": 976.0
      },
      {
        "date": "2024-08-01",
        "rank": 63,
        "elo": 976.0
      },
      {
        "date": "2024-09-01",
        "rank": 63,
        "elo": 976.0
      },
      {
        "date": "2024-10-01",
        "rank": 64,
        "elo": 976.0
      },
      {
        "date": "2024-11-01",
        "rank": 68,
        "elo": 976.0
      },
      {
        "date": "2024-12-01",
        "rank": 69,
        "elo": 976.0
      },
      {
        "date": "2025-01-01",
        "rank": 69,
        "elo": 976.0
      },
      {
        "date": "2025-02-01",
        "rank": 69,
        "elo": 976.0
      },
      {
        "date": "2025-03-01",
        "rank": 68,
        "elo": 976.0
      },
      {
        "date": "2025-04-01",
        "rank": 66,
        "elo": 976.0
      },
      {
        "date": "2025-05-01",
        "rank": 66,
        "elo": 976.0
      },
      {
        "date": "2025-06-01",
        "rank": 66,
        "elo": 976.0
      },
      {
        "date": "2025-07-01",
        "rank": 65,
        "elo": 976.0
      },
      {
        "date": "2025-08-01",
        "rank": 64,
        "elo": 976.0
      },
      {
        "date": "2025-09-01",
        "rank": 64,
        "elo": 976.0
      },
      {
        "date": "2025-10-01",
        "rank": 66,
        "elo": 976.0
      },
      {
        "date": "2025-11-01",
        "rank": 66,
        "elo": 976.0
      },
      {
        "date": "2025-12-01",
        "rank": 66,
        "elo": 976.0
      },
      {
        "date": "2026-01-01",
        "rank": 66,
        "elo": 976.0
      },
      {
        "date": "2026-02-01",
        "rank": 67,
        "elo": 976.0
      },
      {
        "date": "2026-03-01",
        "rank": 67,
        "elo": 976.0
      },
      {
        "date": "2026-04-01",
        "rank": 68,
        "elo": 976.0
      },
      {
        "date": "2026-05-01",
        "rank": 68,
        "elo": 976.0
      },
      {
        "date": "2026-06-01",
        "rank": 67,
        "elo": 976.0
      }
    ]
  },
  "fights": [
    {
      "date": "2024-03-23",
      "weight_class": "flw",
      "weight_class_name": "Flyweight",
      "opponent_id": "b1f21ce050035d58",
      "opponent_name": "Andre Lima",
      "result": "dq",
      "outcome": "L",
      "p4p_before": 1000.0,
      "p4p_after": 976.0,
      "p4p_delta": -24.0,
      "div_before": 1000.0,
      "div_after": 976.0,
      "div_delta": -24.0
    }
  ]
}