{
  "id": "8c0580d4fff106c1",
  "name": "Kelvin Gastelum",
  "slug": "kelvin-gastelum",
  "last_fight_date": "2026-04-11",
  "active_current_mode": true,
  "divisions": [
    "mw",
    "ww"
  ],
  "division_names": {
    "mw": "Middleweight",
    "ww": "Welterweight"
  },
  "rank_history": {
    "p4p": [
      {
        "date": "2013-04-01",
        "rank": 243,
        "elo": 1011.2
      },
      {
        "date": "2013-05-01",
        "rank": 237,
        "elo": 1011.2
      },
      {
        "date": "2013-06-01",
        "rank": 243,
        "elo": 1011.2
      },
      {
        "date": "2013-07-01",
        "rank": 244,
        "elo": 1011.2
      },
      {
        "date": "2013-08-01",
        "rank": 119,
        "elo": 1032.67
      },
      {
        "date": "2013-09-01",
        "rank": 118,
        "elo": 1032.67
      },
      {
        "date": "2013-10-01",
        "rank": 121,
        "elo": 1032.67
      },
      {
        "date": "2013-11-01",
        "rank": 122,
        "elo": 1032.67
      },
      {
        "date": "2013-12-01",
        "rank": 121,
        "elo": 1032.67
      },
      {
        "date": "2014-01-01",
        "rank": 117,
        "elo": 1032.67
      },
      {
        "date": "2014-02-01",
        "rank": 121,
        "elo": 1032.67
      },
      {
        "date": "2014-03-01",
        "rank": 84,
        "elo": 1043.98
      },
      {
        "date": "2014-04-01",
        "rank": 84,
        "elo": 1043.98
      },
      {
        "date": "2014-05-01",
        "rank": 85,
        "elo": 1043.98
      },
      {
        "date": "2014-06-01",
        "rank": 58,
        "elo": 1059.45
      },
      {
        "date": "2014-07-01",
        "rank": 64,
        "elo": 1059.45
      },
      {
        "date": "2014-08-01",
        "rank": 63,
        "elo": 1059.45
      },
      {
        "date": "2014-09-01",
        "rank": 64,
        "elo": 1059.45
      },
      {
        "date": "2014-10-01",
        "rank": 62,
        "elo": 1059.45
      },
      {
        "date": "2014-11-01",
        "rank": 38,
        "elo": 1078.4
      },
      {
        "date": "2014-12-01",
        "rank": 38,
        "elo": 1078.4
      },
      {
        "date": "2015-01-01",
        "rank": 60,
        "elo": 1060.17
      },
      {
        "date": "2015-02-01",
        "rank": 61,
        "elo": 1060.17
      },
      {
        "date": "2015-03-01",
        "rank": 58,
        "elo": 1060.17
      },
      {
        "date": "2015-04-01",
        "rank": 58,
        "elo": 1060.17
      },
      {
        "date": "2015-05-01",
        "rank": 58,
        "elo": 1060.17
      },
      {
        "date": "2015-06-01",
        "rank": 42,
        "elo": 1077.66
      },
      {
        "date": "2015-07-01",
        "rank": 41,
        "elo": 1077.66
      },
      {
        "date": "2015-08-01",
        "rank": 39,
        "elo": 1077.66
      },
      {
        "date": "2015-09-01",
        "rank": 38,
        "elo": 1077.66
      },
      {
        "date": "2015-10-01",
        "rank": 39,
        "elo": 1077.66
      },
      {
        "date": "2015-11-01",
        "rank": 73,
        "elo": 1060.38
      },
      {
        "date": "2015-12-01",
        "rank": 71,
        "elo": 1060.38
      },
      {
        "date": "2016-01-01",
        "rank": 73,
        "elo": 1060.38
      },
      {
        "date": "2016-02-01",
        "rank": 72,
        "elo": 1060.38
      },
      {
        "date": "2016-03-01",
        "rank": 72,
        "elo": 1060.38
      },
      {
        "date": "2016-04-01",
        "rank": 73,
        "elo": 1060.38
      },
      {
        "date": "2016-05-01",
        "rank": 71,
        "elo": 1060.38
      },
      {
        "date": "2016-06-01",
        "rank": 69,
        "elo": 1060.38
      },
      {
        "date": "2016-07-01",
        "rank": 45,
        "elo": 1078.88
      },
      {
        "date": "2016-08-01",
        "rank": 45,
        "elo": 1078.88
      },
      {
        "date": "2016-09-01",
        "rank": 45,
        "elo": 1078.88
      },
      {
        "date": "2016-10-01",
        "rank": 46,
        "elo": 1078.88
      },
      {
        "date": "2016-11-01",
        "rank": 46,
        "elo": 1078.88
      },
      {
        "date": "2016-12-01",
        "rank": 34,
        "elo": 1096.55
      },
      {
        "date": "2017-01-01",
        "rank": 34,
        "elo": 1096.55
      },
      {
        "date": "2017-02-01",
        "rank": 34,
        "elo": 1096.55
      },
      {
        "date": "2017-03-01",
        "rank": 34,
        "elo": 1096.55
      },
      {
        "date": "2017-04-01",
        "rank": 32,
        "elo": 1096.55
      },
      {
        "date": "2017-05-01",
        "rank": 31,
        "elo": 1096.55
      },
      {
        "date": "2017-06-01",
        "rank": 31,
        "elo": 1096.55
      },
      {
        "date": "2017-07-01",
        "rank": 73,
        "elo": 1063.21
      },
      {
        "date": "2017-08-01",
        "rank": 74,
        "elo": 1063.21
      },
      {
        "date": "2017-09-01",
        "rank": 74,
        "elo": 1063.21
      },
      {
        "date": "2017-10-01",
        "rank": 77,
        "elo": 1063.21
      },
      {
        "date": "2017-11-01",
        "rank": 42,
        "elo": 1085.38
      },
      {
        "date": "2017-12-01",
        "rank": 42,
        "elo": 1085.38
      },
      {
        "date": "2018-01-01",
        "rank": 44,
        "elo": 1085.38
      },
      {
        "date": "2018-02-01",
        "rank": 45,
        "elo": 1085.38
      },
      {
        "date": "2018-03-01",
        "rank": 45,
        "elo": 1085.38
      },
      {
        "date": "2018-04-01",
        "rank": 46,
        "elo": 1085.38
      },
      {
        "date": "2018-05-01",
        "rank": 32,
        "elo": 1097.19
      },
      {
        "date": "2018-06-01",
        "rank": 31,
        "elo": 1097.19
      },
      {
        "date": "2018-07-01",
        "rank": 30,
        "elo": 1097.19
      },
      {
        "date": "2018-08-01",
        "rank": 29,
        "elo": 1097.19
      },
      {
        "date": "2018-09-01",
        "rank": 30,
        "elo": 1097.19
      },
      {
        "date": "2018-10-01",
        "rank": 31,
        "elo": 1097.19
      },
      {
        "date": "2018-11-01",
        "rank": 33,
        "elo": 1097.19
      },
      {
        "date": "2018-12-01",
        "rank": 34,
        "elo": 1097.19
      },
      {
        "date": "2019-01-01",
        "rank": 37,
        "elo": 1097.19
      },
      {
        "date": "2019-02-01",
        "rank": 38,
        "elo": 1097.19
      },
      {
        "date": "2019-03-01",
        "rank": 41,
        "elo": 1097.19
      },
      {
        "date": "2019-04-01",
        "rank": 71,
        "elo": 1072.47
      },
      {
        "date": "2019-05-01",
        "rank": 68,
        "elo": 1072.47
      },
      {
        "date": "2019-06-01",
        "rank": 68,
        "elo": 1072.47
      },
      {
        "date": "2019-07-01",
        "rank": 70,
        "elo": 1072.47
      },
      {
        "date": "2019-08-01",
        "rank": 72,
        "elo": 1072.47
      },
      {
        "date": "2019-09-01",
        "rank": 72,
        "elo": 1072.47
      },
      {
        "date": "2019-10-01",
        "rank": 74,
        "elo": 1072.47
      },
      {
        "date": "2019-11-01",
        "rank": 120,
        "elo": 1053.65
      },
      {
        "date": "2019-12-01",
        "rank": 121,
        "elo": 1053.65
      },
      {
        "date": "2020-01-01",
        "rank": 121,
        "elo": 1053.65
      },
      {
        "date": "2020-02-01",
        "rank": 121,
        "elo": 1053.65
      },
      {
        "date": "2020-03-01",
        "rank": 119,
        "elo": 1053.65
      },
      {
        "date": "2020-04-01",
        "rank": 119,
        "elo": 1053.65
      },
      {
        "date": "2020-05-01",
        "rank": 118,
        "elo": 1053.65
      },
      {
        "date": "2020-06-01",
        "rank": 117,
        "elo": 1053.65
      },
      {
        "date": "2020-07-01",
        "rank": 288,
        "elo": 1020.8
      },
      {
        "date": "2020-08-01",
        "rank": 290,
        "elo": 1020.8
      },
      {
        "date": "2020-09-01",
        "rank": 290,
        "elo": 1020.8
      },
      {
        "date": "2020-10-01",
        "rank": 292,
        "elo": 1020.8
      },
      {
        "date": "2020-11-01",
        "rank": 297,
        "elo": 1020.8
      },
      {
        "date": "2020-12-01",
        "rank": 297,
        "elo": 1020.8
      },
      {
        "date": "2021-01-01",
        "rank": 301,
        "elo": 1020.8
      },
      {
        "date": "2021-02-01",
        "rank": 185,
        "elo": 1037.38
      },
      {
        "date": "2021-03-01",
        "rank": 189,
        "elo": 1037.38
      },
      {
        "date": "2021-04-01",
        "rank": 330,
        "elo": 1020.29
      },
      {
        "date": "2021-05-01",
        "rank": 327,
        "elo": 1020.29
      },
      {
        "date": "2021-06-01",
        "rank": 328,
        "elo": 1020.29
      },
      {
        "date": "2021-07-01",
        "rank": 329,
        "elo": 1020.29
      },
      {
        "date": "2021-08-01",
        "rank": 545,
        "elo": 995.84
      },
      {
        "date": "2021-09-01",
        "rank": 548,
        "elo": 995.84
      },
      {
        "date": "2021-10-01",
        "rank": 555,
        "elo": 995.84
      },
      {
        "date": "2021-11-01",
        "rank": 552,
        "elo": 995.84
      },
      {
        "date": "2021-12-01",
        "rank": 551,
        "elo": 995.84
      },
      {
        "date": "2022-01-01",
        "rank": 557,
        "elo": 995.84
      },
      {
        "date": "2022-02-01",
        "rank": 555,
        "elo": 995.84
      },
      {
        "date": "2022-03-01",
        "rank": 552,
        "elo": 995.84
      },
      {
        "date": "2022-04-01",
        "rank": 561,
        "elo": 995.84
      },
      {
        "date": "2022-05-01",
        "rank": 566,
        "elo": 995.84
      },
      {
        "date": "2022-06-01",
        "rank": 566,
        "elo": 995.84
      },
      {
        "date": "2022-07-01",
        "rank": 565,
        "elo": 995.84
      },
      {
        "date": "2022-08-01",
        "rank": 565,
        "elo": 995.84
      },
      {
        "date": "2022-09-01",
        "rank": 569,
        "elo": 995.84
      },
      {
        "date": "2022-10-01",
        "rank": 574,
        "elo": 995.84
      },
      {
        "date": "2022-11-01",
        "rank": 574,
        "elo": 995.84
      },
      {
        "date": "2022-12-01",
        "rank": 570,
        "elo": 995.84
      },
      {
        "date": "2023-01-01",
        "rank": 574,
        "elo": 995.84
      },
      {
        "date": "2023-02-01",
        "rank": 584,
        "elo": 995.84
      },
      {
        "date": "2023-03-01",
        "rank": 591,
        "elo": 995.84
      },
      {
        "date": "2023-04-01",
        "rank": 422,
        "elo": 1014.47
      },
      {
        "date": "2023-05-01",
        "rank": 423,
        "elo": 1014.47
      },
      {
        "date": "2023-06-01",
        "rank": 423,
        "elo": 1014.47
      },
      {
        "date": "2023-07-01",
        "rank": 425,
        "elo": 1014.47
      },
      {
        "date": "2023-08-01",
        "rank": 427,
        "elo": 1014.47
      },
      {
        "date": "2023-09-01",
        "rank": 428,
        "elo": 1014.47
      },
      {
        "date": "2023-10-01",
        "rank": 435,
        "elo": 1014.47
      },
      {
        "date": "2023-11-01",
        "rank": 434,
        "elo": 1014.47
      },
      {
        "date": "2023-12-01",
        "rank": 743,
        "elo": 985.95
      },
      {
        "date": "2024-01-01",
        "rank": 742,
        "elo": 985.95
      },
      {
        "date": "2024-02-01",
        "rank": 748,
        "elo": 985.95
      },
      {
        "date": "2024-03-01",
        "rank": 752,
        "elo": 985.95
      },
      {
        "date": "2024-04-01",
        "rank": 758,
        "elo": 985.95
      },
      {
        "date": "2024-05-01",
        "rank": 757,
        "elo": 985.95
      },
      {
        "date": "2024-06-01",
        "rank": 531,
        "elo": 1003.02
      },
      {
        "date": "2024-07-01",
        "rank": 532,
        "elo": 1003.02
      },
      {
        "date": "2024-08-01",
        "rank": 535,
        "elo": 1003.02
      },
      {
        "date": "2024-09-01",
        "rank": 535,
        "elo": 1003.02
      },
      {
        "date": "2024-10-01",
        "rank": 534,
        "elo": 1003.02
      },
      {
        "date": "2024-11-01",
        "rank": 542,
        "elo": 1003.02
      },
      {
        "date": "2024-12-01",
        "rank": 540,
        "elo": 1003.02
      },
      {
        "date": "2025-01-01",
        "rank": 535,
        "elo": 1003.02
      },
      {
        "date": "2025-02-01",
        "rank": 538,
        "elo": 1003.02
      },
      {
        "date": "2025-03-01",
        "rank": 539,
        "elo": 1003.02
      },
      {
        "date": "2025-04-01",
        "rank": 540,
        "elo": 1003.02
      },
      {
        "date": "2025-05-01",
        "rank": 536,
        "elo": 1003.02
      },
      {
        "date": "2025-06-01",
        "rank": 827,
        "elo": 982.03
      },
      {
        "date": "2025-07-01",
        "rank": 820,
        "elo": 982.03
      },
      {
        "date": "2025-08-01",
        "rank": 826,
        "elo": 982.03
      },
      {
        "date": "2025-09-01",
        "rank": 635,
        "elo": 995.08
      },
      {
        "date": "2025-10-01",
        "rank": 630,
        "elo": 995.08
      },
      {
        "date": "2025-11-01",
        "rank": 632,
        "elo": 995.08
      },
      {
        "date": "2025-12-01",
        "rank": 634,
        "elo": 995.08
      },
      {
        "date": "2026-01-01",
        "rank": 633,
        "elo": 995.08
      },
      {
        "date": "2026-02-01",
        "rank": 639,
        "elo": 995.08
      },
      {
        "date": "2026-03-01",
        "rank": 638,
        "elo": 995.08
      },
      {
        "date": "2026-04-01",
        "rank": 1387,
        "elo": 966.85
      },
      {
        "date": "2026-05-01",
        "rank": 1386,
        "elo": 966.85
      },
      {
        "date": "2026-06-01",
        "rank": 1385,
        "elo": 966.85
      }
    ],
    "mw": [
      {
        "date": "2013-04-01",
        "rank": 65,
        "elo": 1011.2
      },
      {
        "date": "2013-05-01",
        "rank": 66,
        "elo": 1011.2
      },
      {
        "date": "2013-06-01",
        "rank": 67,
        "elo": 1011.2
      },
      {
        "date": "2013-07-01",
        "rank": 68,
        "elo": 1011.2
      },
      {
        "date": "2013-08-01",
        "rank": 67,
        "elo": 1011.2
      },
      {
        "date": "2013-09-01",
        "rank": 66,
        "elo": 1011.2
      },
      {
        "date": "2013-10-01",
        "rank": 68,
        "elo": 1011.2
      },
      {
        "date": "2013-11-01",
        "rank": 65,
        "elo": 1011.2
      },
      {
        "date": "2013-12-01",
        "rank": 66,
        "elo": 1011.2
      },
      {
        "date": "2014-01-01",
        "rank": 65,
        "elo": 1011.2
      },
      {
        "date": "2014-02-01",
        "rank": 65,
        "elo": 1011.2
      },
      {
        "date": "2014-03-01",
        "rank": 65,
        "elo": 1011.2
      },
      {
        "date": "2014-04-01",
        "rank": 67,
        "elo": 1011.2
      },
      {
        "date": "2014-05-01",
        "rank": 70,
        "elo": 1011.2
      },
      {
        "date": "2014-06-01",
        "rank": 70,
        "elo": 1011.2
      },
      {
        "date": "2014-07-01",
        "rank": 72,
        "elo": 1011.2
      },
      {
        "date": "2014-08-01",
        "rank": 73,
        "elo": 1011.2
      },
      {
        "date": "2014-09-01",
        "rank": 73,
        "elo": 1011.2
      },
      {
        "date": "2014-10-01",
        "rank": 73,
        "elo": 1011.2
      },
      {
        "date": "2014-11-01",
        "rank": 75,
        "elo": 1011.2
      },
      {
        "date": "2014-12-01",
        "rank": 75,
        "elo": 1011.2
      },
      {
        "date": "2015-01-01",
        "rank": 74,
        "elo": 1011.2
      },
      {
        "date": "2015-02-01",
        "rank": 75,
        "elo": 1011.2
      },
      {
        "date": "2015-03-01",
        "rank": 74,
        "elo": 1011.2
      },
      {
        "date": "2015-04-01",
        "rank": 76,
        "elo": 1011.2
      },
      {
        "date": "2015-05-01",
        "rank": 75,
        "elo": 1011.2
      },
      {
        "date": "2015-06-01",
        "rank": 20,
        "elo": 1035.22
      },
      {
        "date": "2015-07-01",
        "rank": 21,
        "elo": 1035.22
      },
      {
        "date": "2015-08-01",
        "rank": 21,
        "elo": 1035.22
      },
      {
        "date": "2015-09-01",
        "rank": 22,
        "elo": 1035.22
      },
      {
        "date": "2015-10-01",
        "rank": 22,
        "elo": 1035.22
      },
      {
        "date": "2015-11-01",
        "rank": 21,
        "elo": 1035.22
      },
      {
        "date": "2015-12-01",
        "rank": 20,
        "elo": 1035.22
      },
      {
        "date": "2016-01-01",
        "rank": 21,
        "elo": 1035.22
      },
      {
        "date": "2016-02-01",
        "rank": 21,
        "elo": 1035.22
      },
      {
        "date": "2016-03-01",
        "rank": 22,
        "elo": 1035.22
      },
      {
        "date": "2016-04-01",
        "rank": 21,
        "elo": 1035.22
      },
      {
        "date": "2016-05-01",
        "rank": 21,
        "elo": 1035.22
      },
      {
        "date": "2016-06-01",
        "rank": 23,
        "elo": 1035.22
      },
      {
        "date": "2016-07-01",
        "rank": 22,
        "elo": 1035.22
      },
      {
        "date": "2016-08-01",
        "rank": 22,
        "elo": 1035.22
      },
      {
        "date": "2016-09-01",
        "rank": 22,
        "elo": 1035.22
      },
      {
        "date": "2016-10-01",
        "rank": 22,
        "elo": 1035.22
      },
      {
        "date": "2016-11-01",
        "rank": 23,
        "elo": 1035.22
      },
      {
        "date": "2016-12-01",
        "rank": 13,
        "elo": 1055.42
      },
      {
        "date": "2017-01-01",
        "rank": 14,
        "elo": 1055.42
      },
      {
        "date": "2017-02-01",
        "rank": 14,
        "elo": 1055.42
      },
      {
        "date": "2017-03-01",
        "rank": 15,
        "elo": 1055.42
      },
      {
        "date": "2017-04-01",
        "rank": 15,
        "elo": 1055.42
      },
      {
        "date": "2017-05-01",
        "rank": 14,
        "elo": 1055.42
      },
      {
        "date": "2017-06-01",
        "rank": 14,
        "elo": 1055.42
      },
      {
        "date": "2017-07-01",
        "rank": 31,
        "elo": 1025.23
      },
      {
        "date": "2017-08-01",
        "rank": 32,
        "elo": 1025.23
      },
      {
        "date": "2017-09-01",
        "rank": 32,
        "elo": 1025.23
      },
      {
        "date": "2017-10-01",
        "rank": 30,
        "elo": 1025.23
      },
      {
        "date": "2017-11-01",
        "rank": 15,
        "elo": 1048.37
      },
      {
        "date": "2017-12-01",
        "rank": 15,
        "elo": 1048.37
      },
      {
        "date": "2018-01-01",
        "rank": 15,
        "elo": 1048.37
      },
      {
        "date": "2018-02-01",
        "rank": 15,
        "elo": 1048.37
      },
      {
        "date": "2018-03-01",
        "rank": 15,
        "elo": 1048.37
      },
      {
        "date": "2018-04-01",
        "rank": 15,
        "elo": 1048.37
      },
      {
        "date": "2018-05-01",
        "rank": 12,
        "elo": 1061.34
      },
      {
        "date": "2018-06-01",
        "rank": 12,
        "elo": 1061.34
      },
      {
        "date": "2018-07-01",
        "rank": 12,
        "elo": 1061.34
      },
      {
        "date": "2018-08-01",
        "rank": 12,
        "elo": 1061.34
      },
      {
        "date": "2018-09-01",
        "rank": 12,
        "elo": 1061.34
      },
      {
        "date": "2018-10-01",
        "rank": 12,
        "elo": 1061.34
      },
      {
        "date": "2018-11-01",
        "rank": 12,
        "elo": 1061.34
      },
      {
        "date": "2018-12-01",
        "rank": 13,
        "elo": 1061.34
      },
      {
        "date": "2019-01-01",
        "rank": 13,
        "elo": 1061.34
      },
      {
        "date": "2019-02-01",
        "rank": 13,
        "elo": 1061.34
      },
      {
        "date": "2019-03-01",
        "rank": 13,
        "elo": 1061.34
      },
      {
        "date": "2019-04-01",
        "rank": 21,
        "elo": 1039.11
      },
      {
        "date": "2019-05-01",
        "rank": 23,
        "elo": 1039.11
      },
      {
        "date": "2019-06-01",
        "rank": 23,
        "elo": 1039.11
      },
      {
        "date": "2019-07-01",
        "rank": 24,
        "elo": 1039.11
      },
      {
        "date": "2019-08-01",
        "rank": 25,
        "elo": 1039.11
      },
      {
        "date": "2019-09-01",
        "rank": 24,
        "elo": 1039.11
      },
      {
        "date": "2019-10-01",
        "rank": 24,
        "elo": 1039.11
      },
      {
        "date": "2019-11-01",
        "rank": 58,
        "elo": 1020.42
      },
      {
        "date": "2019-12-01",
        "rank": 59,
        "elo": 1020.42
      },
      {
        "date": "2020-01-01",
        "rank": 59,
        "elo": 1020.42
      },
      {
        "date": "2020-02-01",
        "rank": 59,
        "elo": 1020.42
      },
      {
        "date": "2020-03-01",
        "rank": 59,
        "elo": 1020.42
      },
      {
        "date": "2020-04-01",
        "rank": 59,
        "elo": 1020.42
      },
      {
        "date": "2020-05-01",
        "rank": 59,
        "elo": 1020.42
      },
      {
        "date": "2020-06-01",
        "rank": 59,
        "elo": 1020.42
      },
      {
        "date": "2020-07-01",
        "rank": 122,
        "elo": 991.16
      },
      {
        "date": "2020-08-01",
        "rank": 121,
        "elo": 991.16
      },
      {
        "date": "2020-09-01",
        "rank": 120,
        "elo": 991.16
      },
      {
        "date": "2020-10-01",
        "rank": 124,
        "elo": 991.16
      },
      {
        "date": "2020-11-01",
        "rank": 125,
        "elo": 991.16
      },
      {
        "date": "2020-12-01",
        "rank": 126,
        "elo": 991.16
      },
      {
        "date": "2021-01-01",
        "rank": 126,
        "elo": 991.16
      },
      {
        "date": "2021-02-01",
        "rank": 92,
        "elo": 1009.13
      },
      {
        "date": "2021-03-01",
        "rank": 91,
        "elo": 1009.13
      },
      {
        "date": "2021-04-01",
        "rank": 118,
        "elo": 993.68
      },
      {
        "date": "2021-05-01",
        "rank": 119,
        "elo": 993.68
      },
      {
        "date": "2021-06-01",
        "rank": 121,
        "elo": 993.68
      },
      {
        "date": "2021-07-01",
        "rank": 119,
        "elo": 993.68
      },
      {
        "date": "2021-08-01",
        "rank": 200,
        "elo": 973.4
      },
      {
        "date": "2021-09-01",
        "rank": 200,
        "elo": 973.4
      },
      {
        "date": "2021-10-01",
        "rank": 200,
        "elo": 973.4
      },
      {
        "date": "2021-11-01",
        "rank": 202,
        "elo": 973.4
      },
      {
        "date": "2021-12-01",
        "rank": 202,
        "elo": 973.4
      },
      {
        "date": "2022-01-01",
        "rank": 203,
        "elo": 973.4
      },
      {
        "date": "2022-02-01",
        "rank": 205,
        "elo": 973.4
      },
      {
        "date": "2022-03-01",
        "rank": 205,
        "elo": 973.4
      },
      {
        "date": "2022-04-01",
        "rank": 208,
        "elo": 973.4
      },
      {
        "date": "2022-05-01",
        "rank": 208,
        "elo": 973.4
      },
      {
        "date": "2022-06-01",
        "rank": 208,
        "elo": 973.4
      },
      {
        "date": "2022-07-01",
        "rank": 207,
        "elo": 973.4
      },
      {
        "date": "2022-08-01",
        "rank": 208,
        "elo": 973.4
      },
      {
        "date": "2022-09-01",
        "rank": 210,
        "elo": 973.4
      },
      {
        "date": "2022-10-01",
        "rank": 207,
        "elo": 973.4
      },
      {
        "date": "2022-11-01",
        "rank": 207,
        "elo": 973.4
      },
      {
        "date": "2022-12-01",
        "rank": 208,
        "elo": 973.4
      },
      {
        "date": "2023-01-01",
        "rank": 209,
        "elo": 973.4
      },
      {
        "date": "2023-02-01",
        "rank": 208,
        "elo": 973.4
      },
      {
        "date": "2023-03-01",
        "rank": 208,
        "elo": 973.4
      },
      {
        "date": "2023-04-01",
        "rank": 131,
        "elo": 993.1
      },
      {
        "date": "2023-05-01",
        "rank": 130,
        "elo": 993.1
      },
      {
        "date": "2023-06-01",
        "rank": 129,
        "elo": 993.1
      },
      {
        "date": "2023-07-01",
        "rank": 130,
        "elo": 993.1
      },
      {
        "date": "2023-08-01",
        "rank": 130,
        "elo": 993.1
      },
      {
        "date": "2023-09-01",
        "rank": 129,
        "elo": 993.1
      },
      {
        "date": "2023-10-01",
        "rank": 131,
        "elo": 993.1
      },
      {
        "date": "2023-11-01",
        "rank": 131,
        "elo": 993.1
      },
      {
        "date": "2023-12-01",
        "rank": 131,
        "elo": 993.1
      },
      {
        "date": "2024-01-01",
        "rank": 132,
        "elo": 993.1
      },
      {
        "date": "2024-02-01",
        "rank": 131,
        "elo": 993.1
      },
      {
        "date": "2024-03-01",
        "rank": 132,
        "elo": 993.1
      },
      {
        "date": "2024-04-01",
        "rank": 133,
        "elo": 993.1
      },
      {
        "date": "2024-05-01",
        "rank": 131,
        "elo": 993.1
      },
      {
        "date": "2024-06-01",
        "rank": 100,
        "elo": 1009.42
      },
      {
        "date": "2024-07-01",
        "rank": 100,
        "elo": 1009.42
      },
      {
        "date": "2024-08-01",
        "rank": 102,
        "elo": 1009.42
      },
      {
        "date": "2024-09-01",
        "rank": 102,
        "elo": 1009.42
      },
      {
        "date": "2024-10-01",
        "rank": 103,
        "elo": 1009.42
      },
      {
        "date": "2024-11-01",
        "rank": 104,
        "elo": 1009.42
      },
      {
        "date": "2024-12-01",
        "rank": 104,
        "elo": 1009.42
      },
      {
        "date": "2025-01-01",
        "rank": 104,
        "elo": 1009.42
      },
      {
        "date": "2025-02-01",
        "rank": 105,
        "elo": 1009.42
      },
      {
        "date": "2025-03-01",
        "rank": 109,
        "elo": 1009.42
      },
      {
        "date": "2025-04-01",
        "rank": 109,
        "elo": 1009.42
      },
      {
        "date": "2025-05-01",
        "rank": 108,
        "elo": 1009.42
      },
      {
        "date": "2025-06-01",
        "rank": 148,
        "elo": 987.93
      },
      {
        "date": "2025-07-01",
        "rank": 148,
        "elo": 987.93
      },
      {
        "date": "2025-08-01",
        "rank": 150,
        "elo": 987.93
      },
      {
        "date": "2025-09-01",
        "rank": 118,
        "elo": 1000.83
      },
      {
        "date": "2025-10-01",
        "rank": 119,
        "elo": 1000.83
      },
      {
        "date": "2025-11-01",
        "rank": 119,
        "elo": 1000.83
      },
      {
        "date": "2025-12-01",
        "rank": 120,
        "elo": 1000.83
      },
      {
        "date": "2026-01-01",
        "rank": 120,
        "elo": 1000.83
      },
      {
        "date": "2026-02-01",
        "rank": 123,
        "elo": 1000.83
      },
      {
        "date": "2026-03-01",
        "rank": 124,
        "elo": 1000.83
      },
      {
        "date": "2026-04-01",
        "rank": 250,
        "elo": 969.56
      },
      {
        "date": "2026-05-01",
        "rank": 250,
        "elo": 969.56
      },
      {
        "date": "2026-06-01",
        "rank": 250,
        "elo": 969.56
      }
    ],
    "ww": [
      {
        "date": "2013-08-01",
        "rank": 29,
        "elo": 1022.2
      },
      {
        "date": "2013-09-01",
        "rank": 30,
        "elo": 1022.2
      },
      {
        "date": "2013-10-01",
        "rank": 31,
        "elo": 1022.2
      },
      {
        "date": "2013-11-01",
        "rank": 34,
        "elo": 1022.2
      },
      {
        "date": "2013-12-01",
        "rank": 33,
        "elo": 1022.2
      },
      {
        "date": "2014-01-01",
        "rank": 32,
        "elo": 1022.2
      },
      {
        "date": "2014-02-01",
        "rank": 32,
        "elo": 1022.2
      },
      {
        "date": "2014-03-01",
        "rank": 28,
        "elo": 1033.72
      },
      {
        "date": "2014-04-01",
        "rank": 27,
        "elo": 1033.72
      },
      {
        "date": "2014-05-01",
        "rank": 29,
        "elo": 1033.72
      },
      {
        "date": "2014-06-01",
        "rank": 15,
        "elo": 1048.94
      },
      {
        "date": "2014-07-01",
        "rank": 16,
        "elo": 1048.94
      },
      {
        "date": "2014-08-01",
        "rank": 16,
        "elo": 1048.94
      },
      {
        "date": "2014-09-01",
        "rank": 16,
        "elo": 1048.94
      },
      {
        "date": "2014-10-01",
        "rank": 16,
        "elo": 1048.94
      },
      {
        "date": "2014-11-01",
        "rank": 6,
        "elo": 1068.28
      },
      {
        "date": "2014-12-01",
        "rank": 6,
        "elo": 1068.28
      },
      {
        "date": "2015-01-01",
        "rank": 17,
        "elo": 1050.48
      },
      {
        "date": "2015-02-01",
        "rank": 17,
        "elo": 1050.48
      },
      {
        "date": "2015-03-01",
        "rank": 16,
        "elo": 1050.48
      },
      {
        "date": "2015-04-01",
        "rank": 17,
        "elo": 1050.48
      },
      {
        "date": "2015-05-01",
        "rank": 18,
        "elo": 1050.48
      },
      {
        "date": "2015-06-01",
        "rank": 18,
        "elo": 1050.48
      },
      {
        "date": "2015-07-01",
        "rank": 20,
        "elo": 1050.48
      },
      {
        "date": "2015-08-01",
        "rank": 20,
        "elo": 1050.48
      },
      {
        "date": "2015-09-01",
        "rank": 20,
        "elo": 1050.48
      },
      {
        "date": "2015-10-01",
        "rank": 21,
        "elo": 1050.48
      },
      {
        "date": "2015-11-01",
        "rank": 37,
        "elo": 1034.49
      },
      {
        "date": "2015-12-01",
        "rank": 36,
        "elo": 1034.49
      },
      {
        "date": "2016-01-01",
        "rank": 34,
        "elo": 1034.49
      },
      {
        "date": "2016-02-01",
        "rank": 34,
        "elo": 1034.49
      },
      {
        "date": "2016-03-01",
        "rank": 33,
        "elo": 1034.49
      },
      {
        "date": "2016-04-01",
        "rank": 35,
        "elo": 1034.49
      },
      {
        "date": "2016-05-01",
        "rank": 35,
        "elo": 1034.49
      },
      {
        "date": "2016-06-01",
        "rank": 35,
        "elo": 1034.49
      },
      {
        "date": "2016-07-01",
        "rank": 17,
        "elo": 1054.08
      },
      {
        "date": "2016-08-01",
        "rank": 18,
        "elo": 1054.08
      },
      {
        "date": "2016-09-01",
        "rank": 18,
        "elo": 1054.08
      },
      {
        "date": "2016-10-01",
        "rank": 18,
        "elo": 1054.08
      },
      {
        "date": "2016-11-01",
        "rank": 20,
        "elo": 1054.08
      },
      {
        "date": "2016-12-01",
        "rank": 21,
        "elo": 1054.08
      },
      {
        "date": "2017-01-01",
        "rank": 21,
        "elo": 1054.08
      },
      {
        "date": "2017-02-01",
        "rank": 23,
        "elo": 1054.08
      },
      {
        "date": "2017-03-01",
        "rank": 22,
        "elo": 1054.08
      },
      {
        "date": "2017-04-01",
        "rank": 22,
        "elo": 1054.08
      },
      {
        "date": "2017-05-01",
        "rank": 22,
        "elo": 1054.08
      },
      {
        "date": "2017-06-01",
        "rank": 22,
        "elo": 1054.08
      },
      {
        "date": "2017-07-01",
        "rank": 20,
        "elo": 1054.08
      },
      {
        "date": "2017-08-01",
        "rank": 20,
        "elo": 1054.08
      },
      {
        "date": "2017-09-01",
        "rank": 21,
        "elo": 1054.08
      },
      {
        "date": "2017-10-01",
        "rank": 22,
        "elo": 1054.08
      },
      {
        "date": "2017-11-01",
        "rank": 20,
        "elo": 1054.08
      },
      {
        "date": "2017-12-01",
        "rank": 21,
        "elo": 1054.08
      },
      {
        "date": "2018-01-01",
        "rank": 21,
        "elo": 1054.08
      },
      {
        "date": "2018-02-01",
        "rank": 20,
        "elo": 1054.08
      },
      {
        "date": "2018-03-01",
        "rank": 20,
        "elo": 1054.08
      },
      {
        "date": "2018-04-01",
        "rank": 20,
        "elo": 1054.08
      },
      {
        "date": "2018-05-01",
        "rank": 22,
        "elo": 1054.08
      },
      {
        "date": "2018-06-01",
        "rank": 21,
        "elo": 1054.08
      },
      {
        "date": "2018-07-01",
        "rank": 21,
        "elo": 1054.08
      },
      {
        "date": "2018-08-01",
        "rank": 21,
        "elo": 1054.08
      },
      {
        "date": "2018-09-01",
        "rank": 23,
        "elo": 1054.08
      },
      {
        "date": "2018-10-01",
        "rank": 23,
        "elo": 1054.08
      },
      {
        "date": "2018-11-01",
        "rank": 23,
        "elo": 1054.08
      },
      {
        "date": "2018-12-01",
        "rank": 24,
        "elo": 1054.08
      },
      {
        "date": "2019-01-01",
        "rank": 24,
        "elo": 1054.08
      },
      {
        "date": "2019-02-01",
        "rank": 24,
        "elo": 1054.08
      },
      {
        "date": "2019-03-01",
        "rank": 21,
        "elo": 1054.08
      },
      {
        "date": "2019-04-01",
        "rank": 21,
        "elo": 1054.08
      },
      {
        "date": "2019-05-01",
        "rank": 20,
        "elo": 1054.08
      },
      {
        "date": "2019-06-01",
        "rank": 20,
        "elo": 1054.08
      },
      {
        "date": "2019-07-01",
        "rank": 21,
        "elo": 1054.08
      },
      {
        "date": "2019-08-01",
        "rank": 22,
        "elo": 1054.08
      },
      {
        "date": "2019-09-01",
        "rank": 22,
        "elo": 1054.08
      },
      {
        "date": "2019-10-01",
        "rank": 22,
        "elo": 1054.08
      },
      {
        "date": "2019-11-01",
        "rank": 24,
        "elo": 1054.08
      },
      {
        "date": "2019-12-01",
        "rank": 24,
        "elo": 1054.08
      },
      {
        "date": "2020-01-01",
        "rank": 24,
        "elo": 1054.08
      },
      {
        "date": "2020-02-01",
        "rank": 24,
        "elo": 1054.08
      },
      {
        "date": "2020-03-01",
        "rank": 26,
        "elo": 1054.08
      },
      {
        "date": "2020-04-01",
        "rank": 26,
        "elo": 1054.08
      },
      {
        "date": "2020-05-01",
        "rank": 26,
        "elo": 1054.08
      },
      {
        "date": "2020-06-01",
        "rank": 26,
        "elo": 1054.08
      },
      {
        "date": "2020-07-01",
        "rank": 25,
        "elo": 1054.08
      },
      {
        "date": "2020-08-01",
        "rank": 25,
        "elo": 1054.08
      },
      {
        "date": "2020-09-01",
        "rank": 25,
        "elo": 1054.08
      },
      {
        "date": "2020-10-01",
        "rank": 24,
        "elo": 1054.08
      },
      {
        "date": "2020-11-01",
        "rank": 26,
        "elo": 1054.08
      },
      {
        "date": "2020-12-01",
        "rank": 24,
        "elo": 1054.08
      },
      {
        "date": "2021-01-01",
        "rank": 25,
        "elo": 1054.08
      },
      {
        "date": "2021-02-01",
        "rank": 25,
        "elo": 1054.08
      },
      {
        "date": "2021-03-01",
        "rank": 25,
        "elo": 1054.08
      },
      {
        "date": "2021-04-01",
        "rank": 24,
        "elo": 1054.08
      },
      {
        "date": "2021-05-01",
        "rank": 24,
        "elo": 1054.08
      },
      {
        "date": "2021-06-01",
        "rank": 23,
        "elo": 1054.08
      },
      {
        "date": "2021-07-01",
        "rank": 23,
        "elo": 1054.08
      },
      {
        "date": "2021-08-01",
        "rank": 23,
        "elo": 1054.08
      },
      {
        "date": "2021-09-01",
        "rank": 24,
        "elo": 1054.08
      },
      {
        "date": "2021-10-01",
        "rank": 23,
        "elo": 1054.08
      },
      {
        "date": "2021-11-01",
        "rank": 23,
        "elo": 1054.08
      },
      {
        "date": "2021-12-01",
        "rank": 22,
        "elo": 1054.08
      },
      {
        "date": "2022-01-01",
        "rank": 23,
        "elo": 1054.08
      },
      {
        "date": "2022-02-01",
        "rank": 24,
        "elo": 1054.08
      },
      {
        "date": "2022-03-01",
        "rank": 24,
        "elo": 1054.08
      },
      {
        "date": "2022-04-01",
        "rank": 25,
        "elo": 1054.08
      },
      {
        "date": "2022-05-01",
        "rank": 25,
        "elo": 1054.08
      },
      {
        "date": "2022-06-01",
        "rank": 25,
        "elo": 1054.08
      },
      {
        "date": "2022-07-01",
        "rank": 25,
        "elo": 1054.08
      },
      {
        "date": "2022-08-01",
        "rank": 26,
        "elo": 1054.08
      },
      {
        "date": "2022-09-01",
        "rank": 26,
        "elo": 1054.08
      },
      {
        "date": "2022-10-01",
        "rank": 26,
        "elo": 1054.08
      },
      {
        "date": "2022-11-01",
        "rank": 27,
        "elo": 1054.08
      },
      {
        "date": "2022-12-01",
        "rank": 28,
        "elo": 1054.08
      },
      {
        "date": "2023-01-01",
        "rank": 27,
        "elo": 1054.08
      },
      {
        "date": "2023-02-01",
        "rank": 26,
        "elo": 1054.08
      },
      {
        "date": "2023-03-01",
        "rank": 27,
        "elo": 1054.08
      },
      {
        "date": "2023-04-01",
        "rank": 26,
        "elo": 1054.08
      },
      {
        "date": "2023-05-01",
        "rank": 26,
        "elo": 1054.08
      },
      {
        "date": "2023-06-01",
        "rank": 27,
        "elo": 1054.08
      },
      {
        "date": "2023-07-01",
        "rank": 28,
        "elo": 1054.08
      },
      {
        "date": "2023-08-01",
        "rank": 27,
        "elo": 1054.08
      },
      {
        "date": "2023-09-01",
        "rank": 27,
        "elo": 1054.08
      },
      {
        "date": "2023-10-01",
        "rank": 27,
        "elo": 1054.08
      },
      {
        "date": "2023-11-01",
        "rank": 27,
        "elo": 1054.08
      },
      {
        "date": "2023-12-01",
        "rank": 63,
        "elo": 1022.03
      },
      {
        "date": "2024-01-01",
        "rank": 63,
        "elo": 1022.03
      },
      {
        "date": "2024-02-01",
        "rank": 62,
        "elo": 1022.03
      },
      {
        "date": "2024-03-01",
        "rank": 61,
        "elo": 1022.03
      },
      {
        "date": "2024-04-01",
        "rank": 61,
        "elo": 1022.03
      },
      {
        "date": "2024-05-01",
        "rank": 61,
        "elo": 1022.03
      },
      {
        "date": "2024-06-01",
        "rank": 62,
        "elo": 1022.03
      },
      {
        "date": "2024-07-01",
        "rank": 65,
        "elo": 1022.03
      },
      {
        "date": "2024-08-01",
        "rank": 66,
        "elo": 1022.03
      },
      {
        "date": "2024-09-01",
        "rank": 64,
        "elo": 1022.03
      },
      {
        "date": "2024-10-01",
        "rank": 66,
        "elo": 1022.03
      },
      {
        "date": "2024-11-01",
        "rank": 65,
        "elo": 1022.03
      },
      {
        "date": "2024-12-01",
        "rank": 64,
        "elo": 1022.03
      },
      {
        "date": "2025-01-01",
        "rank": 66,
        "elo": 1022.03
      },
      {
        "date": "2025-02-01",
        "rank": 65,
        "elo": 1022.03
      },
      {
        "date": "2025-03-01",
        "rank": 64,
        "elo": 1022.03
      },
      {
        "date": "2025-04-01",
        "rank": 63,
        "elo": 1022.03
      },
      {
        "date": "2025-05-01",
        "rank": 63,
        "elo": 1022.03
      },
      {
        "date": "2025-06-01",
        "rank": 65,
        "elo": 1022.03
      },
      {
        "date": "2025-07-01",
        "rank": 65,
        "elo": 1022.03
      },
      {
        "date": "2025-08-01",
        "rank": 63,
        "elo": 1022.03
      },
      {
        "date": "2025-09-01",
        "rank": 63,
        "elo": 1022.03
      },
      {
        "date": "2025-10-01",
        "rank": 62,
        "elo": 1022.03
      },
      {
        "date": "2025-11-01",
        "rank": 65,
        "elo": 1022.03
      },
      {
        "date": "2025-12-01",
        "rank": 65,
        "elo": 1022.03
      },
      {
        "date": "2026-01-01",
        "rank": 65,
        "elo": 1022.03
      },
      {
        "date": "2026-02-01",
        "rank": 66,
        "elo": 1022.03
      },
      {
        "date": "2026-03-01",
        "rank": 66,
        "elo": 1022.03
      },
      {
        "date": "2026-04-01",
        "rank": 68,
        "elo": 1022.03
      },
      {
        "date": "2026-05-01",
        "rank": 68,
        "elo": 1022.03
      },
      {
        "date": "2026-06-01",
        "rank": 68,
        "elo": 1022.03
      }
    ]
  },
  "fights": [
    {
      "date": "2026-04-11",
      "weight_class": "mw",
      "weight_class_name": "Middleweight",
      "opponent_id": "6d4b63c767106d3a",
      "opponent_name": "Vicente Luque",
      "result": "sub",
      "outcome": "L",
      "p4p_before": 995.08,
      "p4p_after": 966.85,
      "p4p_delta": -28.23,
      "div_before": 1000.83,
      "div_after": 969.56,
      "div_delta": -31.27
    },
    {
      "date": "2025-09-13",
      "weight_class": "mw",
      "weight_class_name": "Middleweight",
      "opponent_id": "71505842fb6455c3",
      "opponent_name": "Dustin Stoltzfus",
      "result": "ud",
      "outcome": "W",
      "p4p_before": 982.03,
      "p4p_after": 995.08,
      "p4p_delta": 13.05,
      "div_before": 987.93,
      "div_after": 1000.83,
      "div_delta": 12.9
    },
    {
      "date": "2025-06-07",
      "weight_class": "mw",
      "weight_class_name": "Middleweight",
      "opponent_id": "c1085e1701b13eca",
      "opponent_name": "Joe Pyfer",
      "result": "ud",
      "outcome": "L",
      "p4p_before": 1003.02,
      "p4p_after": 982.03,
      "p4p_delta": -20.99,
      "div_before": 1009.42,
      "div_after": 987.93,
      "div_delta": -21.49
    },
    {
      "date": "2024-06-22",
      "weight_class": "mw",
      "weight_class_name": "Middleweight",
      "opponent_id": "8a1f3b5c526cd6e6",
      "opponent_name": "Daniel Rodriguez",
      "result": "ud",
      "outcome": "W",
      "p4p_before": 985.95,
      "p4p_after": 1003.02,
      "p4p_delta": 17.07,
      "div_before": 993.1,
      "div_after": 1009.42,
      "div_delta": 16.32
    },
    {
      "date": "2023-12-02",
      "weight_class": "ww",
      "weight_class_name": "Welterweight",
      "opponent_id": "45f7cb591c3ab00b",
      "opponent_name": "Sean Brady",
      "result": "sub",
      "outcome": "L",
      "p4p_before": 1014.47,
      "p4p_after": 985.95,
      "p4p_delta": -28.52,
      "div_before": 1054.08,
      "div_after": 1022.03,
      "div_delta": -32.05
    },
    {
      "date": "2023-04-08",
      "weight_class": "mw",
      "weight_class_name": "Middleweight",
      "opponent_id": "5442f1bc4b47eaf3",
      "opponent_name": "Chris Curtis",
      "result": "ud",
      "outcome": "W",
      "p4p_before": 995.84,
      "p4p_after": 1014.47,
      "p4p_delta": 18.63,
      "div_before": 973.4,
      "div_after": 993.1,
      "div_delta": 19.7
    },
    {
      "date": "2021-08-21",
      "weight_class": "mw",
      "weight_class_name": "Middleweight",
      "opponent_id": "13a0275fa13c4d26",
      "opponent_name": "Jared Cannonier",
      "result": "ud",
      "outcome": "L",
      "p4p_before": 1020.29,
      "p4p_after": 995.84,
      "p4p_delta": -24.45,
      "div_before": 993.68,
      "div_after": 973.4,
      "div_delta": -20.28
    },
    {
      "date": "2021-04-17",
      "weight_class": "mw",
      "weight_class_name": "Middleweight",
      "opponent_id": "e1147d3d2dabe1ce",
      "opponent_name": "Robert Whittaker",
      "result": "ud",
      "outcome": "L",
      "p4p_before": 1037.38,
      "p4p_after": 1020.29,
      "p4p_delta": -17.09,
      "div_before": 1009.13,
      "div_after": 993.68,
      "div_delta": -15.45
    },
    {
      "date": "2021-02-13",
      "weight_class": "mw",
      "weight_class_name": "Middleweight",
      "opponent_id": "2e585c701f72fe55",
      "opponent_name": "Ian Heinisch",
      "result": "ud",
      "outcome": "W",
      "p4p_before": 1020.8,
      "p4p_after": 1037.38,
      "p4p_delta": 16.58,
      "div_before": 991.16,
      "div_after": 1009.13,
      "div_delta": 17.97
    },
    {
      "date": "2020-07-18",
      "weight_class": "mw",
      "weight_class_name": "Middleweight",
      "opponent_id": "0a1942069c9ad6b6",
      "opponent_name": "Jack Hermansson",
      "result": "sub",
      "outcome": "L",
      "p4p_before": 1053.65,
      "p4p_after": 1020.8,
      "p4p_delta": -32.85,
      "div_before": 1020.42,
      "div_after": 991.16,
      "div_delta": -29.26
    },
    {
      "date": "2019-11-02",
      "weight_class": "mw",
      "weight_class_name": "Middleweight",
      "opponent_id": "9ce6d5a03af801b7",
      "opponent_name": "Darren Till",
      "result": "sd",
      "outcome": "L",
      "p4p_before": 1072.47,
      "p4p_after": 1053.65,
      "p4p_delta": -18.82,
      "div_before": 1039.11,
      "div_after": 1020.42,
      "div_delta": -18.69
    },
    {
      "date": "2019-04-13",
      "weight_class": "mw",
      "weight_class_name": "Middleweight",
      "opponent_id": "1338e2c7480bdf9e",
      "opponent_name": "Israel Adesanya",
      "result": "ud",
      "outcome": "L",
      "p4p_before": 1097.19,
      "p4p_after": 1072.47,
      "p4p_delta": -24.72,
      "div_before": 1061.34,
      "div_after": 1039.11,
      "div_delta": -22.23
    },
    {
      "date": "2018-05-12",
      "weight_class": "mw",
      "weight_class_name": "Middleweight",
      "opponent_id": "7a703c565ccaa18f",
      "opponent_name": "Jacare Souza",
      "result": "sd",
      "outcome": "W",
      "p4p_before": 1085.38,
      "p4p_after": 1097.19,
      "p4p_delta": 11.81,
      "div_before": 1048.37,
      "div_after": 1061.34,
      "div_delta": 12.97
    },
    {
      "date": "2017-11-25",
      "weight_class": "mw",
      "weight_class_name": "Middleweight",
      "opponent_id": "2b93ebd9f5417ad2",
      "opponent_name": "Michael Bisping",
      "result": "ko/tko",
      "outcome": "W",
      "p4p_before": 1063.21,
      "p4p_after": 1085.38,
      "p4p_delta": 22.17,
      "div_before": 1025.23,
      "div_after": 1048.37,
      "div_delta": 23.14
    },
    {
      "date": "2017-07-22",
      "weight_class": "mw",
      "weight_class_name": "Middleweight",
      "opponent_id": "3a8176e15b9887c1",
      "opponent_name": "Chris Weidman",
      "result": "sub",
      "outcome": "L",
      "p4p_before": 1096.55,
      "p4p_after": 1063.21,
      "p4p_delta": -33.34,
      "div_before": 1055.42,
      "div_after": 1025.23,
      "div_delta": -30.19
    },
    {
      "date": "2016-12-10",
      "weight_class": "mw",
      "weight_class_name": "Middleweight",
      "opponent_id": "3c660c90d48fc80d",
      "opponent_name": "Tim Kennedy",
      "result": "ko/tko",
      "outcome": "W",
      "p4p_before": 1078.88,
      "p4p_after": 1096.55,
      "p4p_delta": 17.67,
      "div_before": 1035.22,
      "div_after": 1055.42,
      "div_delta": 20.2
    },
    {
      "date": "2016-07-09",
      "weight_class": "ww",
      "weight_class_name": "Welterweight",
      "opponent_id": "0941df56f6ac954b",
      "opponent_name": "Johny Hendricks",
      "result": "ud",
      "outcome": "W",
      "p4p_before": 1060.38,
      "p4p_after": 1078.88,
      "p4p_delta": 18.5,
      "div_before": 1034.49,
      "div_after": 1054.08,
      "div_delta": 19.59
    },
    {
      "date": "2015-11-21",
      "weight_class": "ww",
      "weight_class_name": "Welterweight",
      "opponent_id": "84b3e7d38f2d2ec5",
      "opponent_name": "Neil Magny",
      "result": "sd",
      "outcome": "L",
      "p4p_before": 1077.66,
      "p4p_after": 1060.38,
      "p4p_delta": -17.28,
      "div_before": 1050.48,
      "div_after": 1034.49,
      "div_delta": -15.99
    },
    {
      "date": "2015-06-13",
      "weight_class": "mw",
      "weight_class_name": "Middleweight",
      "opponent_id": "a8e6a69796280f17",
      "opponent_name": "Nate Marquardt",
      "result": "ko/tko",
      "outcome": "W",
      "p4p_before": 1060.17,
      "p4p_after": 1077.66,
      "p4p_delta": 17.49,
      "div_before": 1011.2,
      "div_after": 1035.22,
      "div_delta": 24.02
    },
    {
      "date": "2015-01-31",
      "weight_class": "ww",
      "weight_class_name": "Welterweight",
      "opponent_id": "effd9de9937996f8",
      "opponent_name": "Tyron Woodley",
      "result": "sd",
      "outcome": "L",
      "p4p_before": 1078.4,
      "p4p_after": 1060.17,
      "p4p_delta": -18.23,
      "div_before": 1068.28,
      "div_after": 1050.48,
      "div_delta": -17.8
    },
    {
      "date": "2014-11-15",
      "weight_class": "ww",
      "weight_class_name": "Welterweight",
      "opponent_id": "d81ac739417d7f53",
      "opponent_name": "Jake Ellenberger",
      "result": "sub",
      "outcome": "W",
      "p4p_before": 1059.45,
      "p4p_after": 1078.4,
      "p4p_delta": 18.95,
      "div_before": 1048.94,
      "div_after": 1068.28,
      "div_delta": 19.34
    },
    {
      "date": "2014-06-28",
      "weight_class": "ww",
      "weight_class_name": "Welterweight",
      "opponent_id": "8b5f9ea38184ded3",
      "opponent_name": "Nicholas Musoke",
      "result": "ud",
      "outcome": "W",
      "p4p_before": 1043.98,
      "p4p_after": 1059.45,
      "p4p_delta": 15.47,
      "div_before": 1033.72,
      "div_after": 1048.94,
      "div_delta": 15.22
    },
    {
      "date": "2014-03-15",
      "weight_class": "ww",
      "weight_class_name": "Welterweight",
      "opponent_id": "5b5307450405abf0",
      "opponent_name": "Rick Story",
      "result": "sd",
      "outcome": "W",
      "p4p_before": 1032.67,
      "p4p_after": 1043.98,
      "p4p_delta": 11.31,
      "div_before": 1022.2,
      "div_after": 1033.72,
      "div_delta": 11.52
    },
    {
      "date": "2013-08-28",
      "weight_class": "ww",
      "weight_class_name": "Welterweight",
      "opponent_id": "eee7dafac7d672b5",
      "opponent_name": "Brian Melancon",
      "result": "sub",
      "outcome": "W",
      "p4p_before": 1011.2,
      "p4p_after": 1032.67,
      "p4p_delta": 21.47,
      "div_before": 1000.0,
      "div_after": 1022.2,
      "div_delta": 22.2
    },
    {
      "date": "2013-04-13",
      "weight_class": "mw",
      "weight_class_name": "Middleweight",
      "opponent_id": "65578a75fa7900e3",
      "opponent_name": "Uriah Hall",
      "result": "sd",
      "outcome": "W",
      "p4p_before": 1000.0,
      "p4p_after": 1011.2,
      "p4p_delta": 11.2,
      "div_before": 1000.0,
      "div_after": 1011.2,
      "div_delta": 11.2
    }
  ]
}