{
  "id": "c7d7fda69ec410d3",
  "name": "Kamuela Kirk",
  "slug": "kamuela-kirk",
  "last_fight_date": "2023-07-08",
  "active_current_mode": false,
  "divisions": [
    "fw",
    "lw"
  ],
  "division_names": {
    "fw": "Featherweight",
    "lw": "Lightweight"
  },
  "rank_history": {
    "p4p": [
      {
        "date": "2021-06-01",
        "rank": 359,
        "elo": 1016.9
      },
      {
        "date": "2021-07-01",
        "rank": 364,
        "elo": 1016.9
      },
      {
        "date": "2021-08-01",
        "rank": 366,
        "elo": 1016.9
      },
      {
        "date": "2021-09-01",
        "rank": 363,
        "elo": 1016.9
      },
      {
        "date": "2021-10-01",
        "rank": 367,
        "elo": 1016.9
      },
      {
        "date": "2021-11-01",
        "rank": 367,
        "elo": 1016.9
      },
      {
        "date": "2021-12-01",
        "rank": 361,
        "elo": 1016.9
      },
      {
        "date": "2022-01-01",
        "rank": 365,
        "elo": 1016.9
      },
      {
        "date": "2022-02-01",
        "rank": 371,
        "elo": 1016.9
      },
      {
        "date": "2022-03-01",
        "rank": 735,
        "elo": 982.12
      },
      {
        "date": "2022-04-01",
        "rank": 743,
        "elo": 982.12
      },
      {
        "date": "2022-05-01",
        "rank": 742,
        "elo": 982.12
      },
      {
        "date": "2022-06-01",
        "rank": 747,
        "elo": 982.12
      },
      {
        "date": "2022-07-01",
        "rank": 746,
        "elo": 982.12
      },
      {
        "date": "2022-08-01",
        "rank": 751,
        "elo": 982.12
      },
      {
        "date": "2022-09-01",
        "rank": 758,
        "elo": 982.12
      },
      {
        "date": "2022-10-01",
        "rank": 762,
        "elo": 982.12
      },
      {
        "date": "2022-11-01",
        "rank": 763,
        "elo": 982.12
      },
      {
        "date": "2022-12-01",
        "rank": 763,
        "elo": 982.12
      },
      {
        "date": "2023-01-01",
        "rank": 769,
        "elo": 982.12
      },
      {
        "date": "2023-02-01",
        "rank": 783,
        "elo": 982.12
      },
      {
        "date": "2023-03-01",
        "rank": 789,
        "elo": 982.12
      },
      {
        "date": "2023-04-01",
        "rank": 792,
        "elo": 982.12
      },
      {
        "date": "2023-05-01",
        "rank": 789,
        "elo": 982.12
      },
      {
        "date": "2023-06-01",
        "rank": 785,
        "elo": 982.12
      },
      {
        "date": "2023-07-01",
        "rank": 1477,
        "elo": 957.7
      },
      {
        "date": "2023-08-01",
        "rank": 1473,
        "elo": 957.7
      },
      {
        "date": "2023-09-01",
        "rank": 1485,
        "elo": 957.7
      },
      {
        "date": "2023-10-01",
        "rank": 1482,
        "elo": 957.7
      },
      {
        "date": "2023-11-01",
        "rank": 1482,
        "elo": 957.7
      },
      {
        "date": "2023-12-01",
        "rank": 1485,
        "elo": 957.7
      },
      {
        "date": "2024-01-01",
        "rank": 1488,
        "elo": 957.7
      },
      {
        "date": "2024-02-01",
        "rank": 1496,
        "elo": 957.7
      },
      {
        "date": "2024-03-01",
        "rank": 1511,
        "elo": 957.7
      },
      {
        "date": "2024-04-01",
        "rank": 1518,
        "elo": 957.7
      },
      {
        "date": "2024-05-01",
        "rank": 1517,
        "elo": 957.7
      },
      {
        "date": "2024-06-01",
        "rank": 1515,
        "elo": 957.7
      },
      {
        "date": "2024-07-01",
        "rank": 1515,
        "elo": 957.7
      },
      {
        "date": "2024-08-01",
        "rank": 1519,
        "elo": 957.7
      },
      {
        "date": "2024-09-01",
        "rank": 1515,
        "elo": 957.7
      },
      {
        "date": "2024-10-01",
        "rank": 1517,
        "elo": 957.7
      },
      {
        "date": "2024-11-01",
        "rank": 1525,
        "elo": 957.7
      },
      {
        "date": "2024-12-01",
        "rank": 1523,
        "elo": 957.7
      },
      {
        "date": "2025-01-01",
        "rank": 1527,
        "elo": 957.7
      },
      {
        "date": "2025-02-01",
        "rank": 1533,
        "elo": 957.7
      },
      {
        "date": "2025-03-01",
        "rank": 1536,
        "elo": 957.7
      },
      {
        "date": "2025-04-01",
        "rank": 1536,
        "elo": 957.7
      },
      {
        "date": "2025-05-01",
        "rank": 1535,
        "elo": 957.7
      },
      {
        "date": "2025-06-01",
        "rank": 1539,
        "elo": 957.7
      },
      {
        "date": "2025-07-01",
        "rank": 1539,
        "elo": 957.7
      },
      {
        "date": "2025-08-01",
        "rank": 1540,
        "elo": 957.7
      },
      {
        "date": "2025-09-01",
        "rank": 1548,
        "elo": 957.7
      },
      {
        "date": "2025-10-01",
        "rank": 1552,
        "elo": 957.7
      },
      {
        "date": "2025-11-01",
        "rank": 1558,
        "elo": 957.7
      },
      {
        "date": "2025-12-01",
        "rank": 1563,
        "elo": 957.7
      },
      {
        "date": "2026-01-01",
        "rank": 1570,
        "elo": 957.7
      },
      {
        "date": "2026-02-01",
        "rank": 1574,
        "elo": 957.7
      },
      {
        "date": "2026-03-01",
        "rank": 1582,
        "elo": 957.7
      },
      {
        "date": "2026-04-01",
        "rank": 1592,
        "elo": 957.7
      },
      {
        "date": "2026-05-01",
        "rank": 1599,
        "elo": 957.7
      },
      {
        "date": "2026-06-01",
        "rank": 1597,
        "elo": 957.7
      }
    ],
    "fw": [
      {
        "date": "2021-06-01",
        "rank": 43,
        "elo": 1016.83
      },
      {
        "date": "2021-07-01",
        "rank": 44,
        "elo": 1016.83
      },
      {
        "date": "2021-08-01",
        "rank": 45,
        "elo": 1016.83
      },
      {
        "date": "2021-09-01",
        "rank": 45,
        "elo": 1016.83
      },
      {
        "date": "2021-10-01",
        "rank": 47,
        "elo": 1016.83
      },
      {
        "date": "2021-11-01",
        "rank": 47,
        "elo": 1016.83
      },
      {
        "date": "2021-12-01",
        "rank": 47,
        "elo": 1016.83
      },
      {
        "date": "2022-01-01",
        "rank": 47,
        "elo": 1016.83
      },
      {
        "date": "2022-02-01",
        "rank": 50,
        "elo": 1016.83
      },
      {
        "date": "2022-03-01",
        "rank": 111,
        "elo": 984.6
      },
      {
        "date": "2022-04-01",
        "rank": 110,
        "elo": 984.6
      },
      {
        "date": "2022-05-01",
        "rank": 110,
        "elo": 984.6
      },
      {
        "date": "2022-06-01",
        "rank": 110,
        "elo": 984.6
      },
      {
        "date": "2022-07-01",
        "rank": 110,
        "elo": 984.6
      },
      {
        "date": "2022-08-01",
        "rank": 110,
        "elo": 984.6
      },
      {
        "date": "2022-09-01",
        "rank": 111,
        "elo": 984.6
      },
      {
        "date": "2022-10-01",
        "rank": 111,
        "elo": 984.6
      },
      {
        "date": "2022-11-01",
        "rank": 111,
        "elo": 984.6
      },
      {
        "date": "2022-12-01",
        "rank": 113,
        "elo": 984.6
      },
      {
        "date": "2023-01-01",
        "rank": 114,
        "elo": 984.6
      },
      {
        "date": "2023-02-01",
        "rank": 118,
        "elo": 984.6
      },
      {
        "date": "2023-03-01",
        "rank": 119,
        "elo": 984.6
      },
      {
        "date": "2023-04-01",
        "rank": 120,
        "elo": 984.6
      },
      {
        "date": "2023-05-01",
        "rank": 119,
        "elo": 984.6
      },
      {
        "date": "2023-06-01",
        "rank": 117,
        "elo": 984.6
      },
      {
        "date": "2023-07-01",
        "rank": 117,
        "elo": 984.6
      },
      {
        "date": "2023-08-01",
        "rank": 116,
        "elo": 984.6
      },
      {
        "date": "2023-09-01",
        "rank": 119,
        "elo": 984.6
      },
      {
        "date": "2023-10-01",
        "rank": 120,
        "elo": 984.6
      },
      {
        "date": "2023-11-01",
        "rank": 122,
        "elo": 984.6
      },
      {
        "date": "2023-12-01",
        "rank": 121,
        "elo": 984.6
      },
      {
        "date": "2024-01-01",
        "rank": 122,
        "elo": 984.6
      },
      {
        "date": "2024-02-01",
        "rank": 122,
        "elo": 984.6
      },
      {
        "date": "2024-03-01",
        "rank": 122,
        "elo": 984.6
      },
      {
        "date": "2024-04-01",
        "rank": 123,
        "elo": 984.6
      },
      {
        "date": "2024-05-01",
        "rank": 123,
        "elo": 984.6
      },
      {
        "date": "2024-06-01",
        "rank": 122,
        "elo": 984.6
      },
      {
        "date": "2024-07-01",
        "rank": 120,
        "elo": 984.6
      },
      {
        "date": "2024-08-01",
        "rank": 122,
        "elo": 984.6
      },
      {
        "date": "2024-09-01",
        "rank": 123,
        "elo": 984.6
      },
      {
        "date": "2024-10-01",
        "rank": 124,
        "elo": 984.6
      },
      {
        "date": "2024-11-01",
        "rank": 123,
        "elo": 984.6
      },
      {
        "date": "2024-12-01",
        "rank": 123,
        "elo": 984.6
      },
      {
        "date": "2025-01-01",
        "rank": 123,
        "elo": 984.6
      },
      {
        "date": "2025-02-01",
        "rank": 124,
        "elo": 984.6
      },
      {
        "date": "2025-03-01",
        "rank": 125,
        "elo": 984.6
      },
      {
        "date": "2025-04-01",
        "rank": 126,
        "elo": 984.6
      },
      {
        "date": "2025-05-01",
        "rank": 128,
        "elo": 984.6
      },
      {
        "date": "2025-06-01",
        "rank": 129,
        "elo": 984.6
      },
      {
        "date": "2025-07-01",
        "rank": 130,
        "elo": 984.6
      },
      {
        "date": "2025-08-01",
        "rank": 131,
        "elo": 984.6
      },
      {
        "date": "2025-09-01",
        "rank": 132,
        "elo": 984.6
      },
      {
        "date": "2025-10-01",
        "rank": 133,
        "elo": 984.6
      },
      {
        "date": "2025-11-01",
        "rank": 134,
        "elo": 984.6
      },
      {
        "date": "2025-12-01",
        "rank": 134,
        "elo": 984.6
      },
      {
        "date": "2026-01-01",
        "rank": 135,
        "elo": 984.6
      },
      {
        "date": "2026-02-01",
        "rank": 136,
        "elo": 984.6
      },
      {
        "date": "2026-03-01",
        "rank": 139,
        "elo": 984.6
      },
      {
        "date": "2026-04-01",
        "rank": 142,
        "elo": 984.6
      },
      {
        "date": "2026-05-01",
        "rank": 143,
        "elo": 984.6
      },
      {
        "date": "2026-06-01",
        "rank": 143,
        "elo": 984.6
      }
    ],
    "lw": [
      {
        "date": "2023-07-01",
        "rank": 244,
        "elo": 974.34
      },
      {
        "date": "2023-08-01",
        "rank": 245,
        "elo": 974.34
      },
      {
        "date": "2023-09-01",
        "rank": 248,
        "elo": 974.34
      },
      {
        "date": "2023-10-01",
        "rank": 249,
        "elo": 974.34
      },
      {
        "date": "2023-11-01",
        "rank": 250,
        "elo": 974.34
      },
      {
        "date": "2023-12-01",
        "rank": 250,
        "elo": 974.34
      },
      {
        "date": "2024-01-01",
        "rank": 251,
        "elo": 974.34
      },
      {
        "date": "2024-02-01",
        "rank": 252,
        "elo": 974.34
      },
      {
        "date": "2024-03-01",
        "rank": 250,
        "elo": 974.34
      },
      {
        "date": "2024-04-01",
        "rank": 249,
        "elo": 974.34
      },
      {
        "date": "2024-05-01",
        "rank": 249,
        "elo": 974.34
      },
      {
        "date": "2024-06-01",
        "rank": 249,
        "elo": 974.34
      },
      {
        "date": "2024-07-01",
        "rank": 250,
        "elo": 974.34
      },
      {
        "date": "2024-08-01",
        "rank": 253,
        "elo": 974.34
      },
      {
        "date": "2024-09-01",
        "rank": 250,
        "elo": 974.34
      },
      {
        "date": "2024-10-01",
        "rank": 250,
        "elo": 974.34
      },
      {
        "date": "2024-11-01",
        "rank": 250,
        "elo": 974.34
      },
      {
        "date": "2024-12-01",
        "rank": 250,
        "elo": 974.34
      },
      {
        "date": "2025-01-01",
        "rank": 250,
        "elo": 974.34
      },
      {
        "date": "2025-02-01",
        "rank": 250,
        "elo": 974.34
      },
      {
        "date": "2025-03-01",
        "rank": 247,
        "elo": 974.34
      },
      {
        "date": "2025-04-01",
        "rank": 248,
        "elo": 974.34
      },
      {
        "date": "2025-05-01",
        "rank": 252,
        "elo": 974.34
      },
      {
        "date": "2025-06-01",
        "rank": 252,
        "elo": 974.34
      },
      {
        "date": "2025-07-01",
        "rank": 252,
        "elo": 974.34
      },
      {
        "date": "2025-08-01",
        "rank": 251,
        "elo": 974.34
      },
      {
        "date": "2025-09-01",
        "rank": 249,
        "elo": 974.34
      },
      {
        "date": "2025-10-01",
        "rank": 249,
        "elo": 974.34
      },
      {
        "date": "2025-11-01",
        "rank": 250,
        "elo": 974.34
      },
      {
        "date": "2025-12-01",
        "rank": 249,
        "elo": 974.34
      },
      {
        "date": "2026-01-01",
        "rank": 251,
        "elo": 974.34
      },
      {
        "date": "2026-02-01",
        "rank": 251,
        "elo": 974.34
      },
      {
        "date": "2026-03-01",
        "rank": 256,
        "elo": 974.34
      },
      {
        "date": "2026-04-01",
        "rank": 260,
        "elo": 974.34
      },
      {
        "date": "2026-05-01",
        "rank": 261,
        "elo": 974.34
      },
      {
        "date": "2026-06-01",
        "rank": 261,
        "elo": 974.34
      }
    ]
  },
  "fights": [
    {
      "date": "2023-07-08",
      "weight_class": "lw",
      "weight_class_name": "Lightweight",
      "opponent_id": "323d4ca260dfa0ba",
      "opponent_name": "Esteban Ribovics",
      "result": "ud",
      "outcome": "L",
      "p4p_before": 982.12,
      "p4p_after": 957.7,
      "p4p_delta": -24.42,
      "div_before": 1000.0,
      "div_after": 974.34,
      "div_delta": -25.66
    },
    {
      "date": "2022-03-12",
      "weight_class": "fw",
      "weight_class_name": "Featherweight",
      "opponent_id": "29af297d9f1de0f8",
      "opponent_name": "Damon Jackson",
      "result": "sub",
      "outcome": "L",
      "p4p_before": 1016.9,
      "p4p_after": 982.12,
      "p4p_delta": -34.78,
      "div_before": 1016.83,
      "div_after": 984.6,
      "div_delta": -32.23
    },
    {
      "date": "2021-06-05",
      "weight_class": "fw",
      "weight_class_name": "Featherweight",
      "opponent_id": "87a1dc546b1c5caf",
      "opponent_name": "Makwan Amirkhani",
      "result": "ud",
      "outcome": "W",
      "p4p_before": 1000.0,
      "p4p_after": 1016.9,
      "p4p_delta": 16.9,
      "div_before": 1000.0,
      "div_after": 1016.83,
      "div_delta": 16.83
    }
  ]
}